Workbook

Sheet SALES REPORT
A1: WEDNESDAY-MARCH 1 | D1: THURSDAY - MAR 2 | G1: FRIDAY - MAR 3 | J1: SATURDAY - MAR 4 | M1: SUNDAY - MAR 5
A2: CASHIER NAME: | B2: Joemar | D2: CASHIER NAME: | E2: ANN | G2: CASHIER NAME: | H2: Elma | J2: CASHIER NAME: | K2: ELMA | M2: CASHIER NAME: | N2: ANN
A3: STAFF: | B3: Christian | C3: Lito | D3: STAFF: | E3: TOY | F3: DEN | G3: STAFF: | H3: Patrick | I3: Sherwin | J3: STAFF: | K3: PAT | L3: DEN | M3: STAFF: | N3: ELMA | O3: MAR
B4: Erwin | C4: Boboy | E4: MAR | F4: BOY | H4: Dhen | N4: TOY | O4: ERWIN
B5: Dhen | E5: SHERWIN | N5: PAT | O5: SHERWIN
A6: GROSS SALE: | C6: ='DAILY STOCKS (W)'!D49+'DAILY STOCKS (W)'!I26 -> 228900 | D6: GROSS SALE: | F6: ='DAILY STOCKS (TH)'!D49+'DAILY STOCKS (TH)'!I26 -> 50583 | G6: GROSS SALE: | I6: ='DAILY STOCKS (F)'!D49+'DAILY STOCKS (F)'!I26 -> 224053 | J6: GROSS SALE: | L6: ='DAILY STOCKS (SAT)'!D49+'DAILY STOCKS (SAT)'!I26 -> 138215 | M6: GROSS SALE: | O6: ='DAILY STOCKS (SUN)'!D49+'DAILY STOCKS (SUN)'!I26 -> 155929
A7: DAILY EXPENSES: | C7: =SUM(B22:B44) -> 5678.26 | D7: DAILY EXPENSES: | F7: =SUM(E22:E44) -> 3620 | G7: DAILY EXPENSES: | I7: =SUM(H22:H44) -> 4350 | J7: DAILY EXPENSES: | L7: =SUM(K22:K44) -> 9200 | M7: DAILY EXPENSES: | O7: =SUM(N22:N44) -> 3330
A8: DISCOUNT: | C8: ='DAILY STOCKS (W)'!AB100 -> 14193 | D8: DISCOUNT: | F8: ='DAILY STOCKS (TH)'!AB105 -> 1276 | G8: DISCOUNT: | I8: ='DAILY STOCKS (F)'!AB105 -> 13960 | J8: DISCOUNT: | L8: ='DAILY STOCKS (SAT)'!AB105 -> 6660 | M8: DISCOUNT: | O8: ='DAILY STOCKS (SUN)'!AB105 -> 8132
A9: NET SALES: | C9: =C6-C7-C8 -> 209028.74 | D9: NET SALES: | F9: =F6-F7-F8 -> 45687 | G9: NET SALES: | I9: =I6-I7-I8 -> 205743 | J9: NET SALES: | L9: =L6-L7-L8 -> 122355 | M9: NET SALES: | O9: =O6-O7-O8 -> 144467
A10: ACCOUNTS RECEIVABLE: | C10: ='DAILY STOCKS (W)'!AC100 -> 111487 | D10: ACCOUNTS RECEIVABLE: | F10: ='DAILY STOCKS (TH)'!AC105 -> 24777 | G10: ACCOUNTS RECEIVABLE: | I10: ='DAILY STOCKS (F)'!AC105 -> 135322 | J10: ACCOUNTS RECEIVABLE: | L10: ='DAILY STOCKS (SAT)'!AC105 -> 39009 | M10: ACCOUNTS RECEIVABLE: | O10: ='DAILY STOCKS (SUN)'!AC105 -> 64639
A11: POST DATED CHECKS: | C11: =sum(C12:C15) -> 44235.78 | D11: POST DATED CHECKS: | F11: =sum(F12:F15) -> 0 | G11: POST DATED CHECKS: | I11: =sum(I12:I15) -> 0 | J11: POST DATED CHECKS: | L11: =sum(L12:L15) -> 40334 | M11: POST DATED CHECKS: | O11: =sum(O12:O15) -> 8172
A12: <CUSTOMER NAME> | B12: <DATE OF CHECK> | C12: <AMOUNT> | D12: <CUSTOMER NAME> | E12: <DATE OF CHECK> | F12: <AMOUNT> | G12: <CUSTOMER NAME> | H12: <DATE OF CHECK> | I12: <AMOUNT> | J12: <CUSTOMER NAME> | K12: <DATE OF CHECK> | L12: <AMOUNT> | M12: <CUSTOMER NAME> | N12: <DATE OF CHECK> | O12: <AMOUNT>
A13: Rowelinda F. Clarino | B13: 44986 | C13: 10152 | J13: BONITA | K13: 44999 | L13: 40334 | M13: ROWELINDA CLARINO | O13: 8172
A14: Natividad P. Blasco | B14: 44993 | C14: 33106.78
A15: LUCASIA COLLECTION | C15: 977
A16: EXPECTED CASH REMIT: | C16: =C9-C10-C11 -> 53305.96 | D16: EXPECTED CASH REMIT: | F16: =F9-F10-F11 -> 20910 | G16: EXPECTED CASH REMIT: | I16: =I9-I10-I11 -> 70421 | J16: EXPECTED CASH REMIT: | L16: =L9-L10-L11 -> 43012 | M16: EXPECTED CASH REMIT: | O16: =O9-O10-O11 -> 71656
A17: ACTUAL CASH REMIT: | C17: 53400 | D17: ACTUAL CASH REMIT: | F17: 21022 | G17: ACTUAL CASH REMIT: | I17: 70506 | J17: ACTUAL CASH REMIT: | L17: 43164 | M17: ACTUAL CASH REMIT: | O17: 70990
A18: SHORT/OVER: | C18: =C17-C16 -> 94.04 | D18: SHORT/OVER: | F18: =F17-F16 -> 112 | G18: SHORT/OVER: | I18: =I17-I16 -> 85 | J18: SHORT/OVER: | L18: =L17-L16 -> 152 | M18: SHORT/OVER: | N18: ` | O18: =O17-O16 -> -666
A20: TOTAL EXPENSES: | D20: TOTAL EXPENSES: | G20: TOTAL EXPENSES: | J20: TOTAL EXPENSES: | M20: TOTAL EXPENSES:
A21: DESCRIPTION | B21: COST | D21: DESCRIPTION | E21: COST | G21: DESCRIPTION | H21: COST | J21: DESCRIPTION | K21: COST | M21: DESCRIPTION | N21: COST
A22: HYUNDAI GAS | B22: 500 | D22: ALLOWANCE TRAK | E22: 750 | G22: HYUNDAI GAS | H22: 800 | J22: ADVANCES SHERWIN | K22: 300 | M22: MEALS | N22: 350
A23: MEALS | B23: 350 | D23: GAS TRAK | E23: 1400 | G23: MEALS | H23: 450 | J23: JOY | K23: 300 | M23: TRICYCLE GAS | N23: 400
A24: TRICYCLE GAS | B24: 500 | D24: HYUNDAI OIL | E24: 150 | G24: ALLOWANCE | H24: 500 | J24: HYUNDAI GAS | K24: 300 | M24: TRUCK ALLOWANCE | N24: 750
A25: ADVANCES ELMA | B25: 1000 | D25: MEALS | E25: 350 | G25: HYUNDAI GAS | H25: 1000 | J25: TRUCK ALLOW | K25: 500 | M25: TRUCK GAS | N25: 1400
A26: ADVANCES PATRICK | B26: 500 | D26: GAS TRYKE | E26: 400 | G26: TRICYCLE GAS | H26: 600 | J26: TRUCK GAS | K26: 1400 | M26: TRANSPORTATION | N26: 50
A27: TOLLGATE TIGAON | B27: 20 | D27: WATER | E27: 70 | G27: FORD GAS | H27: 1000 | J27: MEALS | K27: 200 | M27: CHANGE TIRE | N27: 80
A28: TAX 2307 | B28: 298.26 | D28: HYUNDAI GAS | E28: 500 | J28: PURCHASE | K28: 500 | M28: ADVANCES SHERWIN | N28: 300
A29: LICENSE | B29: 2250 | J29: TRYKE | K29: 300
A30: CAT FOOD | B30: 260 | J30: PRODUCERS | K30: 3800
J31: CHRISTIAN PAYROLL | K31: 1600

Sheet DAILY STOCKS (W)
F1: UPGRADE / SWAP | K1: DAILYSTOCKS MONITORING | X1: DISCOUNTS
A2: PRODUCT NAME | B2: SRP | C2: SOLD | D2: TOTAL SALES | F2: PRODUCT TO SWAP | G2: PURCHASE PRICE | H2: PRODUCT TO BUY | I2: TOTAL SALES | K2: FULL CYLINDER | L2: BEG | M2: PLANTA PURCHASES | N2: PLANTA REFILL | O2: SOLD | P2: REFILL | Q2: SWAP | R2: BORROWED | S2: RETURN | T2: END | U2: AUD | V2: VAR | X2: INVOICE | Y2: NAME | Z2: PARTICULARS | AA2: CASH | AB2: DISCOUNT | AC2: A/R | AD2: AMOUNT
A3: REGULATOR | F3: 11KG PASAK | H3: 11KG RUSKAS | I3: =IF(AND(F3<>"NONE",H3<>"NONE", G3>0),VLOOKUP(H3,$A$52:$B$63,2,FALSE)-G3+VLOOKUP(H3,$A$25:$B$36,2,FALSE),"") | X3: 209921 | Y3: FLORESTA | Z3: NGT | AA3: 1000 | AB3: 13
A4: REGULATOR (PASAK) | B4: 650 | C4: 0 | D4: =C4*B4 -> 0 | F4: NONE | H4: NONE | I4: =IF(AND(F4<>"NONE",H4<>"NONE", G4>0),VLOOKUP(H4,$A$52:$B$63,2,FALSE)-G4+VLOOKUP(H4,$A$25:$B$36,2,FALSE),"") | K4: 2.7KG | L4: 15 | M4: 0 | N4: 46 | O4: =C14 -> 0 | P4: =C26 -> 41 | Q4: =COUNTIF($H$3:$H$25,K4) -> 0 | R4: =C38 -> 0 | S4: 2 | T4: =L4+M4+N4-O4-P4-Q4-R4-S4 -> 18 | U4: 18 | V4: =U4-T4 -> 0 | X4: 209922 | Y4: GASARTE | Z4: 2.7KG | AA4: 289
A5: REGULATOR (RUSKAS) | B5: 375 | C5: 0 | D5: =C5*B5 -> 0 | F5: NONE | H5: NONE | I5: =IF(AND(F5<>"NONE",H5<>"NONE", G5>0),VLOOKUP(H5,$A$52:$B$63,2,FALSE)-G5+VLOOKUP(H5,$A$25:$B$36,2,FALSE),"") | K5: 2.7KG FIESTA | L5: 2 | M5: 0 | N5: 7 | O5: =C15 -> 0 | P5: =C27 -> 1 | Q5: =COUNTIF($H$3:$H$25,K5) -> 0 | R5: =C39 -> 0 | T5: =L5+M5+N5-O5-P5-Q5-R5-S5 -> 8 | U5: 8 | V5: =U5-T5 -> 0 | X5: 209923 | Y5: LEONARDO | Z5: NGT | AA5: 1000 | AB5: 13
A6: OTHERS | F6: NONE | H6: NONE | I6: =IF(AND(F6<>"NONE",H6<>"NONE", G6>0),VLOOKUP(H6,$A$52:$B$63,2,FALSE)-G6+VLOOKUP(H6,$A$25:$B$36,2,FALSE),"") | K6: 7KG PASAK | L6: 6 | M6: 0 | N6: 10 | O6: =C16 -> 0 | P6: =C28 -> 3 | Q6: =COUNTIF($H$3:$H$25,K6) -> 0 | R6: =C40 -> 0 | T6: =L6+M6+N6-O6-P6-Q6-R6-S6 -> 13 | U6: 13 | V6: =U6-T6 -> 0 | X6: 209924 | Y6: ADAYO | Z6: PV | AA6: 1000 | AB6: 13
A7: GS-3 | B7: 650 | C7: 0 | D7: =C7*B7 -> 0 | F7: NONE | H7: NONE | I7: =IF(AND(F7<>"NONE",H7<>"NONE", G7>0),VLOOKUP(H7,$A$52:$B$63,2,FALSE)-G7+VLOOKUP(H7,$A$25:$B$36,2,FALSE),"") | K7: 7KG RUSKAS | L7: 4 | N7: 14 | O7: =C17 -> 0 | P7: =C29 -> 13 | Q7: =COUNTIF($H$3:$H$25,K7) -> 0 | R7: =C41 -> 0 | T7: =L7+M7+N7-O7-P7-Q7-R7-S7 -> 5 | U7: 5 | V7: =U7-T7 -> 0 | X7: 209925 | Y7: SENTINO | Z7: 2.7KG | AA7: 289
A8: HOSE | B8: 180 | C8: 1 | D8: =C8*B8 -> 180 | F8: NONE | H8: NONE | I8: =IF(AND(F8<>"NONE",H8<>"NONE", G8>0),VLOOKUP(H8,$A$52:$B$63,2,FALSE)-G8+VLOOKUP(H8,$A$25:$B$36,2,FALSE),"") | K8: 11KG PASAK | L8: 39 | N8: 72 | O8: =C18 -> 0 | P8: =C30 -> 95 | Q8: =COUNTIF($H$3:$H$25,K8) -> 0 | R8: =C42 -> 0 | S8: 9 | T8: =L8+M8+N8-O8-P8-Q8-R8-S8 -> 7 | U8: 7 | V8: =U8-T8 -> 0 | X8: 209926 | Y8: AYEN | Z8: PV | AA8: 1000 | AB8: 13
A9: CLAMP | B9: 20 | C9: 1 | D9: =C9*B9 -> 20 | F9: NONE | H9: NONE | I9: =IF(AND(F9<>"NONE",H9<>"NONE", G9>0),VLOOKUP(H9,$A$52:$B$63,2,FALSE)-G9+VLOOKUP(H9,$A$25:$B$36,2,FALSE),"") | K9: 11KG RUSKAS | L9: 17 | M9: 0 | N9: 110 | O9: =C19 -> 0 | P9: =C31 -> 96 | Q9: 0 | R9: =C43 -> 0 | S9: 5 | T9: =L9+M9+N9-O9-P9-Q9-R9-S9 -> 26 | U9: 26 | V9: =U9-T9 -> 0 | X9: 209927 | Y9: SABALLA | Z9: 2.7 | AA9: 289
A10: REYNA (SINGLE BURNER) | B10: 650 | C10: 0 | D10: =C10*B10 -> 0 | F10: NONE | H10: NONE | I10: =IF(AND(F10<>"NONE",H10<>"NONE", G10>0),VLOOKUP(H10,$A$52:$B$63,2,FALSE)-G10+VLOOKUP(H10,$A$25:$B$36,2,FALSE),"") | K10: ELITE PASAK | L10: 8 | M10: 0 | O10: =C20 -> 0 | P10: =C32 -> 0 | Q10: =COUNTIF($H$3:$H$25,K10) -> 0 | R10: =C44 -> 0 | T10: =L10+M10+N10-O10-P10-Q10-R10-S10 -> 8 | U10: 8 | V10: =U10-T10 -> 0 | X10: 209928 | Y10: ESTADILLA | Z10: NGT | AA10: 1000 | AB10: 13
A11: REYNA (DOUBLE BURNER) | B11: 1200 | C11: 0 | D11: =C11*B11 -> 0 | F11: NONE | H11: NONE | I11: =IF(AND(F11<>"NONE",H11<>"NONE", G11>0),VLOOKUP(H11,$A$52:$B$63,2,FALSE)-G11+VLOOKUP(H11,$A$25:$B$36,2,FALSE),"") | K11: ELITE RUSKAS | L11: 17 | M11: 0 | O11: =C21 -> 0 | P11: =C33 -> 1 | Q11: =COUNTIF($H$3:$H$25,K11) -> 0 | R11: =C45 -> 0 | T11: =L11+M11+N11-O11-P11-Q11-R11-S11 -> 16 | U11: 16 | V11: =U11-T11 -> 0 | X11: 209929 | Y11: CORANG | Z11: PV | AA11: 1000 | AB11: 13
A12: Y TYPE | B12: 150 | C12: 1 | D12: =C12*B12 -> 150 | F12: NONE | H12: NONE | I12: =IF(AND(F12<>"NONE",H12<>"NONE", G12>0),VLOOKUP(H12,$A$52:$B$63,2,FALSE)-G12+VLOOKUP(H12,$A$25:$B$36,2,FALSE),"") | K12: 22KG | M12: 0 | N12: 5 | O12: =C22 -> 0 | P12: =C34 -> 1 | Q12: =COUNTIF($H$3:$H$25,K12) -> 0 | R12: =C46 -> 0 | T12: =L12+M12+N12-O12-P12-Q12-R12-S12 -> 4 | U12: 4 | V12: =U12-T12 -> 0 | X12: 209930 | Y12: HELEN | Z12: PV | AA12: 977 | AB12: 36
A13: CYLINDER WITH REFILL | F13: NONE | H13: NONE | I13: =IF(AND(F13<>"NONE",H13<>"NONE", G13>0),VLOOKUP(H13,$A$52:$B$63,2,FALSE)-G13+VLOOKUP(H13,$A$25:$B$36,2,FALSE),"") | K13: 50KG BLUE | M13: 0 | O13: =C23 -> 0 | P13: =C35 -> 0 | Q13: =COUNTIF($H$3:$H$25,K13) -> 0 | R13: =C47 -> 0 | T13: =L13+M13+N13-O13-P13-Q13-R13-S13 -> 0 | V13: =U13-T13 -> 0 | X13: 209931 | Y13: SAN ISIDRO | Z13: 4 NGT | AC13: 4052
A14: 2.7KG | B14: =B26+B53 -> 1489 | C14: 0 | D14: =C14*B14 -> 0 | F14: NONE | H14: NONE | I14: =IF(AND(F14<>"NONE",H14<>"NONE", G14>0),VLOOKUP(H14,$A$52:$B$63,2,FALSE)-G14+VLOOKUP(H14,$A$25:$B$36,2,FALSE),"") | K14: 50KG CODED | L14: 2 | M14: 0 | N14: 5 | O14: =C24 -> 0 | P14: =C36 -> 2 | Q14: =COUNTIF($H$3:$H$25,K14) -> 0 | R14: =C48 -> 0 | T14: =L14+M14+N14-O14-P14-Q14-R14-S14 -> 5 | U14: 5 | V14: =U14-T14 -> 0 | Z14: 4 PV | AC14: 4052
A15: 2.7KG FIESTA | B15: =B27+B54 -> 1489 | C15: 0 | D15: =C15*B15 -> 0 | F15: NONE | H15: NONE | I15: =IF(AND(F15<>"NONE",H15<>"NONE", G15>0),VLOOKUP(H15,$A$52:$B$63,2,FALSE)-G15+VLOOKUP(H15,$A$25:$B$36,2,FALSE),"") | X15: 209932 | Y15: CADLAN | Z15: 3 PV | AC15: 3039
A16: 7KG PASAK | B16: =B28+B55 -> 2588 | C16: 0 | D16: =C16*B16 -> 0 | F16: NONE | H16: NONE | I16: =IF(AND(F16<>"NONE",H16<>"NONE", G16>0),VLOOKUP(H16,$A$52:$B$63,2,FALSE)-G16+VLOOKUP(H16,$A$25:$B$36,2,FALSE),"") | Z16: 2 7KG PV | AC16: 1376
A17: 7KG RUSKAS | B17: =B29+B56 -> 2588 | C17: 0 | D17: =C17*B17 -> 0 | F17: NONE | H17: NONE | I17: =IF(AND(F17<>"NONE",H17<>"NONE", G17>0),VLOOKUP(H17,$A$52:$B$63,2,FALSE)-G17+VLOOKUP(H17,$A$25:$B$36,2,FALSE),"") | K17: EMPTY | L17: BEG | M17: PLANTA | N17: REFILL | O17: SWAP | P17: RETURNED | Q17: END | R17: AUD | S17: VAR | X17: 209933 | Y17: DURANTE | Z17: PV | AA17: 963 | AB17: 50
A18: 11KG PASAK | B18: =B30+B57 -> 3013 | C18: 0 | D18: =C18*B18 -> 0 | F18: NONE | H18: NONE | I18: =IF(AND(F18<>"NONE",H18<>"NONE", G18>0),VLOOKUP(H18,$A$52:$B$63,2,FALSE)-G18+VLOOKUP(H18,$A$25:$B$36,2,FALSE),"") | K18: 2.7KG | L18: 54 | M18: =N4 -> 46 | N18: =P4 -> 41 | O18: =countif($F$3:$F$25,K18) -> 0 | Q18: =L18-M18+N18+O18+P18 -> 49 | R18: 49 | S18: =R18-Q18 -> 0 | X18: 209934 | Y18: ODABAR | Z18: NGT | AA18: 963 | AB18: 50
A19: 11KG RUSKAS | B19: =B31+B58 -> 3013 | C19: 0 | D19: =C19*B19 -> 0 | F19: NONE | H19: NONE | I19: =IF(AND(F19<>"NONE",H19<>"NONE", G19>0),VLOOKUP(H19,$A$52:$B$63,2,FALSE)-G19+VLOOKUP(H19,$A$25:$B$36,2,FALSE),"") | K19: 2.7KG FIESTA | L19: 16 | M19: =N5 -> 7 | N19: =P5 -> 1 | O19: =countif($F$3:$F$25,K19) -> 0 | Q19: =L19-M19+N19+O19+P19 -> 10 | R19: 10 | S19: =R19-Q19 -> 0 | X19: 209935 | Y19: CANOY | Z19: NGT | AA19: 963 | AB19: 50
A20: ELITE PASAK | B20: =B32+B59 -> 4738 | C20: 0 | D20: =C20*B20 -> 0 | F20: NONE | H20: NONE | I20: =IF(AND(F20<>"NONE",H20<>"NONE", G20>0),VLOOKUP(H20,$A$52:$B$63,2,FALSE)-G20+VLOOKUP(H20,$A$25:$B$36,2,FALSE),"") | K20: 7KG PASAK | L20: 13 | M20: =N6 -> 10 | N20: =P6 -> 3 | O20: =countif($F$3:$F$25,K20) -> 0 | Q20: =L20-M20+N20+O20+P20 -> 6 | R20: 6 | S20: =R20-Q20 -> 0 | X20: 209936 | Y20: BLASCO | Z20: 15 PV | AA20: 13695 | AB20: 1500
A21: ELITE RUSKAS | B21: =B33+B60 -> 4738 | C21: 0 | D21: =C21*B21 -> 0 | F21: NONE | H21: NONE | I21: =IF(AND(F21<>"NONE",H21<>"NONE", G21>0),VLOOKUP(H21,$A$52:$B$63,2,FALSE)-G21+VLOOKUP(H21,$A$25:$B$36,2,FALSE),"") | K21: 7KG RUSKAS | L21: 27 | M21: =N7 -> 14 | N21: =P7 -> 13 | O21: =countif($F$3:$F$25,K21) -> 0 | Q21: =L21-M21+N21+O21+P21 -> 26 | R21: 26 | S21: =R21-Q21 -> 0 | Z21: 15 NGT | AA21: 13695 | AB21: 1500
A22: 22KG | B22: =B34+B61 -> 5665 | C22: 0 | D22: =C22*B22 -> 0 | F22: NONE | H22: NONE | I22: =IF(AND(F22<>"NONE",H22<>"NONE", G22>0),VLOOKUP(H22,$A$52:$B$63,2,FALSE)-G22+VLOOKUP(H22,$A$25:$B$36,2,FALSE),"") | K22: 11KG PASAK | L22: 133 | M22: =N8 -> 72 | N22: =P8 -> 95 | O22: 0 | P22: 1 | Q22: =L22-M22+N22+O22+P22 -> 157 | R22: 157 | S22: =R22-Q22 -> 0 | X22: 209937 | Y22: NIKKA | Z22: 1 50CODED | AB22: 400 | AC22: 4059
A23: 50KG BLUE | B23: =B35+B62 -> 9459 | C23: 0 | D23: =C23*B23 -> 0 | F23: NONE | H23: NONE | I23: =IF(AND(F23<>"NONE",H23<>"NONE", G23>0),VLOOKUP(H23,$A$52:$B$63,2,FALSE)-G23+VLOOKUP(H23,$A$25:$B$36,2,FALSE),"") | K23: 11KG RUSKAS | L23: 136 | M23: =N9 -> 110 | N23: =C31 -> 96 | O23: =countif($F$3:$F$25,K23) -> 0 | Q23: =L23-M23+N23+O23+P23 -> 122 | R23: 122 | S23: =R23-Q23 -> 0 | Z23: 1 2.7KG | AB23: 21 | AC23: 268
A24: 50KG CODED | B24: =B36+B63 -> 9459 | C24: 0 | D24: =C24*B24 -> 0 | F24: NONE | H24: NONE | I24: =IF(AND(F24<>"NONE",H24<>"NONE", G24>0),VLOOKUP(H24,$A$52:$B$63,2,FALSE)-G24+VLOOKUP(H24,$A$25:$B$36,2,FALSE),"") | K24: ELITE PASAK | L24: 2 | M24: =N10 | N24: =P10 -> 0 | O24: =countif($F$3:$F$25,K24) -> 0 | Q24: =L24-M24+N24+O24+P24 -> 2 | R24: 2 | S24: =R24-Q24 -> 0 | Z24: 5 NGT | AB24: 375 | AC24: 4690
A25: REFILL | F25: NONE | H25: NONE | I25: =IF(AND(F25<>"NONE",H25<>"NONE", G25>0),VLOOKUP(H25,$A$52:$B$63,2,FALSE)-G25+VLOOKUP(H25,$A$25:$B$36,2,FALSE),"") | K25: ELITE RUSKAS | L25: 58 | M25: =N11 | N25: =P11 -> 1 | O25: =countif($F$3:$F$25,K25) -> 0 | Q25: =L25-M25+N25+O25+P25 -> 59 | R25: 59 | S25: =R25-Q25 -> 0 | Z25: 2 PV | AB25: 150 | AC25: 1876
A26: 2.7KG | B26: 289 | C26: 41 | D26: =C26*B26 -> 11849 | F26: TOTAL SALES | I26: =sum(I3:I25) -> 0 | K26: 22KG | L26: 6 | M26: =N12 -> 5 | N26: =P12 -> 1 | O26: =countif($F$3:$F$25,K26) -> 0 | Q26: =L26-M26+N26+O26+P26 -> 2 | R26: 2 | S26: =R26-Q26 -> 0 | Z26: 1 PV ELITE | AB26: 75 | AC26: 963
A27: 2.7KG FIESTA | B27: 289 | C27: 1 | D27: =C27*B27 -> 289 | K27: 50KG BLUE | L27: 23 | M27: =N13 | N27: =P13 -> 0 | O27: =countif($F$3:$F$25,K27) -> 0 | Q27: =L27-M27+N27+O27+P27 -> 23 | R27: 23 | S27: =R27-Q27 -> 0 | X27: 209938 | Y27: P.NAGA | Z27: 1 50KG CODED | AB27: 400 | AC27: 4059
A28: 7KG PASAK | B28: 688 | C28: 3 | D28: =C28*B28 -> 2064 | K28: 50KG CODED | L28: 19 | M28: =N14 -> 5 | N28: =P14 -> 2 | O28: =countif($F$3:$F$25,K28) -> 0 | Q28: =L28-M28+N28+O28+P28 -> 16 | R28: 16 | S28: =R28-Q28 -> 0 | Z28: 10 2.7KG | AB28: 300 | AC28: 2590
A29: 7KG RUSKAS | B29: 688 | C29: 13 | D29: =C29*B29 -> 8944 | Z29: 2 7PV | AB29: 42 | AC29: 1334
A30: 11KG PASAK | B30: 1013 | C30: 95 | D30: =C30*B30 -> 96235 | Z30: 10 NGT | AB30: 750 | AC30: 9380
A31: 11KG RUSKAS | B31: 1013 | C31: 96 | D31: =C31*B31 -> 97248 | K31: ACCESSORIES | L31: BEG | M31: DELIVERY | N31: SOLD | O31: DEFECTIVE | P31: END | Q31: AUD | R31: VAR | Z31: 10 PV | AB31: 750 | AC31: 9380
A32: ELITE PASAK | B32: 1038 | C32: 0 | D32: =C32*B32 -> 0 | K32: REGULATOR | X32: 209939 | Y32: BARILOG | Z32: 2.7KG | AA32: 280 | AB32: 9
A33: ELITE RUSKAS | B33: 1038 | C33: 1 | D33: =C33*B33 -> 1038 | K33: REGULATOR (PASAK) | L33: 0 | M33: 0 | N33: =C4 -> 0 | P33: =L33+M33-N33-O33 -> 0 | Q33: 0 | R33: =Q33-P33 -> 0 | X33: 209940 | Y33: P.DEL ROSARIO | Z33: 10 NGT | AB33: 750 | AC33: 9380
A34: 22KG | B34: 1965 | C34: 1 | D34: =C34*B34 -> 1965 | K34: REGULATOR (RUSKAS) | L34: 12 | M34: 0 | N34: =C5 -> 0 | P34: =L34+M34-N34-O34 -> 12 | Q34: 12 | R34: =Q34-P34 -> 0 | Z34: 7 PV | AB34: 525 | AC34: 6566
A35: 50KG BLUE | B35: 4459 | C35: 0 | D35: =C35*B35 -> 0 | K35: OTHERS | Z35: 4 2.7KG | AB35: 120 | AC35: 1036
A36: 50KG CODED | B36: 4459 | C36: 2 | D36: =C36*B36 -> 8918 | K36: GS-3 | L36: 18 | M36: 0 | N36: =C7 -> 0 | P36: =L36+M36-N36-O36 -> 18 | Q36: 18 | R36: =Q36-P36 -> 0 | X36: 209941 | Y36: NUNEZ | Z36: 1 PV | AA36: 963 | AB36: 50
A37: BORROW | K37: HOSE | L37: 4 | M37: 0 | N37: =C8 -> 1 | P37: =L37+M37-N37-O37 -> 3 | Q37: 3 | R37: =Q37-P37 -> 0 | X37: 209942 | Y37: TAGONTONG | Z37: 1 PV | AA37: 963 | AB37: 50
A38: 2.7KG | B38: =B26 -> 289 | C38: 0 | D38: =C38*B38 -> 0 | K38: CLAMP | L38: 86 | M38: 0 | N38: =C9 -> 1 | P38: =L38+M38-N38-O38 -> 85 | Q38: 85 | R38: =Q38-P38 -> 0 | X38: 209943 | Y38: SANTIAGO | Z38: 2 PV | AA38: 1976 | AB38: 50
A39: 2.7KG FIESTA | B39: =B27 -> 289 | C39: 0 | D39: =C39*B39 -> 0 | K39: REYNA (SINGLE BURNER) | L39: 0 | M39: 0 | N39: =C10 -> 0 | P39: =L39+M39-N39-O39 -> 0 | Q39: 0 | R39: =Q39-P39 -> 0 | X39: 209944 | Y39: HELEN | Z39: 1 2.7KG | AA39: 268 | AB39: 21
A40: 7KG PASAK | B40: =B28 -> 688 | C40: 0 | D40: =C40*B40 -> 0 | K40: REYNA (DOUBLE BURNER) | L40: 0 | M40: 0 | N40: =C11 -> 0 | P40: =L40+M40-N40-O40 -> 0 | Q40: 0 | R40: =Q40-P40 -> 0 | X40: 209945 | Y40: NALLATAN | Z40: 1 PV | AA40: 938 | AB40: 75
A41: 7KG RUSKAS | B41: =B29 -> 688 | C41: 0 | D41: =C41*B41 -> 0 | K41: Y Type | L41: 4 | M41: 0 | N41: =C12 -> 1 | P41: =L41+M41-N41-O41 -> 3 | Q41: 3 | R41: =Q41-P41 -> 0 | X41: 209946 | Y41: ESCREBAN | Z41: 1 7PV | AA41: 688
A42: 11KG PASAK | B42: =B30 -> 1013 | C42: 0 | D42: =C42*B42 -> 0 | X42: 209947 | Y42: MARMOL | Z42: 1 NGT | AA42: 963 | AB42: 50
A43: 11KG RUSKAS | B43: =B31 -> 1013 | C43: 0 | D43: =C43*B43 -> 0 | X43: 209948 | Y43: BLASCO | Z43: 10 2.7KG | AA43: 2680 | AB43: 210
A44: ELITE PASAK | B44: =B32 -> 1038 | C44: 0 | D44: =C44*B44 -> 0 | K44: TOTAL CYLINDER | L44: BEG | M44: END | N44: VAR | O44: COMMENTS | Z44: 4 7PV | AA44: 2668 | AB44: 84
B45: =B33 -> 1038 | C45: 0 | D45: =C45*B45 -> 0 | K45: 2.7KG | L45: =L4+L18 -> 69 | M45: =T4+Q18 -> 67 | N45: =M45-L45 -> -2 | O45: Negative, binalik sa store | Z45: 1 7NGT | AA45: 667 | AB45: 21
A46: 22KG | B46: =B34 -> 1965 | C46: 0 | D46: =C46*B46 -> 0 | K46: 2.7KG FIESTA | L46: =L5+L19 -> 18 | M46: =T5+Q19 -> 18 | N46: =M46-L46 -> 0 | X46: 209949 | Y46: ALCONGA | Z46: 1 NGT | AA46: 988 | AB46: 25
A47: 50KG BLUE | B47: =B35 -> 4459 | C47: 0 | D47: =C47*B47 -> 0 | K47: 7KG (PASAK) | L47: =L6+L20 -> 19 | M47: =T6+Q20 -> 19 | N47: =M47-L47 -> 0 | X47: 209950 | Y47: SAN ISIDRO | Z47: 3 NGT | AC47: 3039
A48: 50KG CODED | B48: =B36 -> 4459 | C48: 0 | D48: =C48*B48 -> 0 | K48: 7KG (RUSKAS) | L48: =L7+L21 -> 31 | M48: =T7+Q21 -> 31 | N48: =M48-L48 -> 0 | Z48: 1 PV | AC48: 1013
A49: TOTAL SALES | D49: =sum(D4:D48) -> 228900 | K49: 11KG (PASAK) | L49: =L8+L22 -> 172 | M49: =T8+Q22 -> 164 | N49: =M49-L49 -> -8 | O49: negative,binalik sa store | X49: 207851 | Y49: ESTA | Z49: 1 NGT | AA49: 963 | AB49: 50
K50: 11KG (RUSKAS) | L50: =L9+L23 -> 153 | M50: =T9+Q23 -> 148 | N50: =M50-L50 -> -5 | O50: negative,binalik sa store | X50: 207852 | Y50: BELZA | Z50: 1 22KG | AA50: 1789 | AB50: 176
K51: ELITE (PASAK) | L51: =L10+L24 -> 10 | M51: =T10+Q24 -> 10 | N51: =M51-L51 -> 0 | X51: 207853 | Y51: LABIOS | Z51: 2 PV | AA51: 1876 | AB51: 150
A52: CYLINDER PRICE LIST | B52: PRICE | K52: ELITE (RUSKAS) | L52: =L11+L25 -> 75 | M52: =T11+Q25 -> 75 | N52: =M52-L52 -> 0 | X52: 207854 | Y52: RANOCO | Z52: 1 NGT | AA52: 963 | AB52: 50
A53: 2.7KG | B53: 1200 | K53: 22KG | L53: =L12+L26 -> 6 | M53: =T12+Q26 -> 6 | N53: =M53-L53 -> 0 | X53: 207855 | Y53: EEB | Z53: 2 PV | AA53: 1876 | AB53: 150
A54: 2.7KG FIESTA | B54: 1200 | K54: 50KG (BLUE) | L54: =L13+L27 -> 23 | M54: =T13+Q27 -> 23 | N54: =M54-L54 -> 0 | Z54: 2 NGT | AA54: 1876 | AB54: 150
A55: 7KG PASAK | B55: 1900 | K55: 50KG (CODED) | L55: =L14+L28 -> 21 | M55: =T14+Q28 -> 21 | N55: =M55-L55 -> 0 | X55: 207856 | Y55: LYCU | Z55: 2 NGT | AA55: 1876 | AB55: 150
A56: 7KG RUSKAS | B56: 1900 | Z56: 2 PV | AA56: 1876 | AB56: 150
A57: 11KG PASAK | B57: 2000 | X57: 207857 | Y57: HARRY | Z57: 2 PV | AA57: 1876 | AB57: 150
A58: 11KG RUSKAS | B58: 2000 | K58: BORROWED | L58: BEG | M58: BORROWED | N58: RETURNED | O58: END | Z58: 2 NGT | AA58: 1876 | AB58: 150
A59: ELITE PASAK | B59: 3700 | K59: 2.7KG | M59: =R4 -> 0 | N59: =P18 | O59: =L59+M59-N59 -> 0 | X59: 207858 | Y59: CABANOS | Z59: 1 2.7KG | AA59: 280 | AB59: 9
A60: ELITE RUSKAS | B60: 3700 | K60: 2.7KG FIESTA | M60: =R5 -> 0 | N60: =P19 | O60: =L60+M60-N60 -> 0 | X60: 207859 | Y60: DE ALDAY | Z60: 3 NGT | AA60: 2814 | AB60: 225
A61: 22KG | B61: 3700 | K61: 7KG (PASAK) | M61: =R6 -> 0 | N61: =P20 | O61: =L61+M61-N61 -> 0 | X61: 207860 | Y61: ROWENSON | Z61: 3 2.7KG | AA61: 804 | AB61: 63
A62: 50KG BLUE | B62: 5000 | K62: 7KG (RUSKAS) | M62: =R7 -> 0 | N62: =P21 | O62: =L62+M62-N62 -> 0 | Z62: 5 PV | AA62: 4540 | AB62: 525
A63: 50KG CODED | B63: 5000 | K63: 11KG (PASAK) | M63: =R8 -> 0 | N63: =P22 -> 1 | O63: =L63+M63-N63 -> -1 | Z63: 5 NGT | AA63: 4540 | AB63: 525
K64: 11KG (RUSKAS) | M64: =R9 -> 0 | N64: =P23 | O64: =L64+M64-N64 -> 0 | X64: 207861 | Y64: A AND L | Z64: 3 NGT | AA64: 2769 | AB64: 270
K65: ELITE (PASAK) | M65: =R10 -> 0 | N65: =P24 | O65: =L65+M65-N65 -> 0 | Z65: 5 PV | AA65: 4615 | AB65: 450
K66: ELITE (RUSKAS) | M66: =R11 -> 0 | N66: =P25 | O66: =L66+M66-N66 -> 0 | Z66: 2 7PV | AA66: 1334 | AB66: 42
K67: 22KG | M67: =R12 -> 0 | N67: =P26 | O67: =L67+M67-N67 -> 0 | Z67: 3 2.7KG | AA67: 804 | AB67: 63
K68: 50KG (BLUE) | M68: =R13 -> 0 | N68: =P27 | O68: =L68+M68-N68 -> 0 | X68: 207862 | Y68: MURA | Z68: 1 PV | AA68: 963 | AB68: 50
K69: 50KG (CODED) | M69: =R14 -> 0 | N69: =P28 | O69: =L69+M69-N69 -> 0 | X69: 207863 | Y69: SAN ISIDRO | Z69: 2 PV | AC69: 2026
X70: 207864 | Y70: CADLAN | Z70: 5 PV | AC70: 5065
Z71: 10 NGT | AC71: 10130
X72: 207865 | Y72: P. SAGNAY | Z72: 1 7PV | AB72: 21 | AC72: 667
Z73: 1 7NGT | AB73: 21 | AC73: 667
Z74: 2 NGT | AB74: 150 | AC74: 1876
Z75: 5 PV | AB75: 375 | AC75: 4690
X76: 207866 | Y76: LUCASIA | Z76: 1 PV | AB76: 75 | AC76: 938
X77: 207867 | Y77: RAZADO | Z77: 1 NGT | AA77: 963 | AB77: 50
X78: 207868 | Y78: P.TIGAON | Z78: 2 2.7KG | AB78: 42 | AC78: 536
Z79: 1 7NGT | AB79: 21 | AC79: 667
Z80: 1 7PV | AB80: 21 | AC80: 667
Z81: 5 PV | AB81: 375 | AC81: 4690
Z82: 5 NGT | AB82: 375 | AC82: 4690
X83: 207869 | Y83: ESPLANA | Z83: 1 NGT | AA83: 988 | AB83: 25
X84: 207870 | Y84: BERMAL | Z84: 1 NGT | AA84: 938 | AB84: 75
X85: 207871 | Y85: YAMSON | Z85: 2 PV | AA85: 1876 | AB85: 150
X86: 207872 | Y86: UTURN | Z86: 1 NGT | AA86: 938 | AB86: 75
X87: 207873 | Y87: RANOU | Z87: 1 NGT | AA87: 963 | AB87: 50
X88: 207874 | Y88: MALLANAON | Z88: 1 PV | AA88: 963 | AB88: 50
X89: 207875 | Y89: BUENAOBRA | Z89: 1 2.7KG | AA89: 280 | AB89: 9
X90: 207876 | Y90: SALIPONG | Z90: 1 F2.7KG | AA90: 280 | AB90: 9
X91: 207877 | Y91: LOZADA | Z91: 1 PV | AA91: 963 | AB91: 50
X92: 207878 | Y92: SAN ISIDRO | Z92: 2 PV | AC92: 2026
X93: 207879 | Y93: ALMA | Z93: 1 2.7KG | AA93: 280 | AB93: 9
X94: 207880 | Y94: PENARANDA | Z94: 1 PV | AA94: 963 | AB94: 50
Z95: 1HOSE | AA95: 180
Z96: 1CLAMP | AA96: 20
Z97: 1 YTYPE | AA97: 150
X100: TOTAL | AA100: =SUM(AA3:AA99) -> 103220 | AB100: =SUM(AB3:AB99) -> 14193 | AC100: =SUM(AC3:AC99) -> 111487

Sheet DAILY STOCKS (TH)
F1: UPGRADE / SWAP | J1: \ | K1: DAILYSTOCKS MONITORING | X1: DISCOUNTS
A2: PRODUCT NAME | B2: SRP | C2: SOLD | D2: TOTAL SALES | F2: PRODUCT TO SWAP | G2: PURCHASE PRICE | H2: PRODUCT TO BUY | I2: TOTAL SALES | K2: FULL CYLINDER | L2: BEG | M2: PLANTA PURCHASES | N2: PLANTA REFILL | O2: SOLD | P2: REFILL | Q2: SWAP | R2: BORROWED | S2: RETURN | T2: END | U2: AUD | V2: VAR | X2: INVOICE | Y2: NAME | Z2: PARTICULARS | AA2: CASH | AB2: DISCOUNT | AC2: A/R | AD2: AMOUNT
A3: REGULATOR | F3: 50KG BLUE | G3: 0 | H3: NONE | I3: =IF(AND(F3<>"NONE",H3<>"NONE", G3>0),VLOOKUP(H3,$A$52:$B$63,2,FALSE)-G3+VLOOKUP(H3,$A$25:$B$36,2,FALSE),"") | X3: 209776 | Y3: PABIA | Z3: 1 2.7KG | AA3: 280
A4: REGULATOR (PASAK) | B4: 650 | C4: 0 | D4: =C4*B4 -> 0 | F4: 50KG BLUE | G4: 0 | H4: NONE | I4: =IF(AND(F4<>"NONE",H4<>"NONE", G4>0),VLOOKUP(H4,$A$52:$B$63,2,FALSE)-G4+VLOOKUP(H4,$A$25:$B$36,2,FALSE),"") | K4: 2.7KG | L4: ='DAILY STOCKS (W)'!U4 -> 18 | M4: 0 | N4: 0 | O4: =C14 -> 0 | P4: =C26 -> 5 | Q4: =COUNTIF($H$3:$H$25,K4) -> 0 | R4: =C38 -> 0 | T4: =L4+M4+N4-O4-P4-Q4-R4-S4 -> 13 | U4: 13 | V4: =U4-T4 -> 0 | X4: 209777 | Y4: PAGASA | Z4: 1 NGT | AA4: 988 | AB4: 25
A5: REGULATOR (RUSKAS) | B5: 375 | C5: 0 | D5: =C5*B5 -> 0 | F5: 50KG BLUE | G5: 0 | H5: NONE | I5: =IF(AND(F5<>"NONE",H5<>"NONE", G5>0),VLOOKUP(H5,$A$52:$B$63,2,FALSE)-G5+VLOOKUP(H5,$A$25:$B$36,2,FALSE),"") | K5: 2.7KG FIESTA | L5: ='DAILY STOCKS (W)'!U5 -> 8 | M5: 0 | N5: 0 | O5: =C15 -> 0 | P5: =C27 -> 1 | Q5: =COUNTIF($H$3:$H$25,K5) -> 0 | R5: =C39 -> 0 | T5: =L5+M5+N5-O5-P5-Q5-R5-S5 -> 7 | U5: 7 | V5: =U5-T5 -> 0 | X5: 209778 | Y5: BERGALA | Z5: 1 2.7KG | AA5: 280
A6: OTHERS | F6: NONE | H6: NONE | I6: =IF(AND(F6<>"NONE",H6<>"NONE", G6>0),VLOOKUP(H6,$A$52:$B$63,2,FALSE)-G6+VLOOKUP(H6,$A$25:$B$36,2,FALSE),"") | K6: 7KG PASAK | L6: ='DAILY STOCKS (W)'!U6 -> 13 | M6: 0 | N6: 0 | O6: =C16 -> 0 | P6: =C28 -> 1 | Q6: =COUNTIF($H$3:$H$25,K6) -> 0 | R6: =C40 -> 0 | T6: =L6+M6+N6-O6-P6-Q6-R6-S6 -> 12 | U6: 12 | V6: =U6-T6 -> 0 | X6: 209779 | Y6: ADOLFO | Z6: 1 PV | AB6: 75 | AC6: 938
A7: GS-3 | B7: 650 | C7: 0 | D7: =C7*B7 -> 0 | F7: NONE | H7: NONE | I7: =IF(AND(F7<>"NONE",H7<>"NONE", G7>0),VLOOKUP(H7,$A$52:$B$63,2,FALSE)-G7+VLOOKUP(H7,$A$25:$B$36,2,FALSE),"") | K7: 7KG RUSKAS | L7: ='DAILY STOCKS (W)'!U7 -> 5 | M7: 0 | N7: 0 | O7: =C17 -> 0 | P7: =C29 -> 0 | Q7: =COUNTIF($H$3:$H$25,K7) -> 0 | R7: =C41 -> 0 | T7: =L7+M7+N7-O7-P7-Q7-R7-S7 -> 5 | U7: 5 | V7: =U7-T7 -> 0 | X7: 209780 | Y7: ABOVE | Z7: 1 PV | AA7: 938 | AB7: 75
A8: HOSE | B8: 180 | C8: 0 | D8: =C8*B8 -> 0 | F8: NONE | H8: NONE | I8: =IF(AND(F8<>"NONE",H8<>"NONE", G8>0),VLOOKUP(H8,$A$52:$B$63,2,FALSE)-G8+VLOOKUP(H8,$A$25:$B$36,2,FALSE),"") | K8: 11KG PASAK | L8: ='DAILY STOCKS (W)'!U8 -> 7 | M8: 0 | N8: 5 | O8: =C18 -> 0 | P8: =C30 -> 12 | Q8: =COUNTIF($H$3:$H$25,K8) -> 0 | R8: =C42 -> 0 | T8: =L8+M8+N8-O8-P8-Q8-R8-S8 -> 0 | U8: 0 | V8: =U8-T8 -> 0 | X8: 209781 | Y8: JOJO | Z8: 1 PV | AA8: 988 | AB8: 25
A9: CLAMP | B9: 20 | C9: 0 | D9: =C9*B9 -> 0 | F9: NONE | H9: NONE | I9: =IF(AND(F9<>"NONE",H9<>"NONE", G9>0),VLOOKUP(H9,$A$52:$B$63,2,FALSE)-G9+VLOOKUP(H9,$A$25:$B$36,2,FALSE),"") | K9: 11KG RUSKAS | L9: ='DAILY STOCKS (W)'!U9 -> 26 | M9: 0 | N9: 2 | O9: =C19 -> 0 | P9: =C31 -> 14 | Q9: =COUNTIF($H$3:$H$25,K9) -> 0 | R9: =C43 -> 0 | T9: =L9+M9+N9-O9-P9-Q9-R9-S9 -> 14 | U9: 15 | V9: =U9-T9 -> 1 | X9: 209782 | Y9: LARGO | Z9: 1 7NGT | AA9: 688
A10: REYNA (SINGLE BURNER) | B10: 650 | C10: 0 | D10: =C10*B10 -> 0 | F10: NONE | H10: NONE | I10: =IF(AND(F10<>"NONE",H10<>"NONE", G10>0),VLOOKUP(H10,$A$52:$B$63,2,FALSE)-G10+VLOOKUP(H10,$A$25:$B$36,2,FALSE),"") | K10: ELITE PASAK | L10: ='DAILY STOCKS (W)'!U10 -> 8 | M10: 0 | N10: 0 | O10: =C20 -> 0 | P10: =C32 -> 0 | Q10: =COUNTIF($H$3:$H$25,K10) -> 0 | R10: =C44 -> 0 | T10: =L10+M10+N10-O10-P10-Q10-R10-S10 -> 8 | U10: 8 | V10: =U10-T10 -> 0 | X10: 209783 | Y10: ASARI | Z10: 1 PV | AA10: 963 | AB10: 50
A11: REYNA (DOUBLE BURNER) | B11: 1200 | C11: 0 | D11: =C11*B11 -> 0 | F11: NONE | H11: NONE | I11: =IF(AND(F11<>"NONE",H11<>"NONE", G11>0),VLOOKUP(H11,$A$52:$B$63,2,FALSE)-G11+VLOOKUP(H11,$A$25:$B$36,2,FALSE),"") | K11: ELITE RUSKAS | L11: ='DAILY STOCKS (W)'!U11 -> 16 | M11: 0 | N11: 0 | O11: =C21 -> 0 | P11: =C33 -> 2 | Q11: =COUNTIF($H$3:$H$25,K11) -> 0 | R11: =C45 -> 0 | T11: =L11+M11+N11-O11-P11-Q11-R11-S11 -> 14 | U11: 14 | V11: =U11-T11 -> 0 | X11: 209784 | Y11: POLANGUI | Z11: 1 NGT | AA11: 963 | AB11: 50
A12: Y TYPE | B12: 150 | C12: 0 | D12: =C12*B12 -> 0 | F12: NONE | H12: NONE | I12: =IF(AND(F12<>"NONE",H12<>"NONE", G12>0),VLOOKUP(H12,$A$52:$B$63,2,FALSE)-G12+VLOOKUP(H12,$A$25:$B$36,2,FALSE),"") | K12: 22KG | L12: ='DAILY STOCKS (W)'!U12 -> 4 | M12: 0 | N12: 0 | O12: =C22 -> 0 | P12: =C34 -> 1 | Q12: =COUNTIF($H$3:$H$25,K12) -> 0 | R12: =C46 -> 0 | T12: =L12+M12+N12-O12-P12-Q12-R12-S12 -> 3 | U12: 3 | V12: =U12-T12 -> 0 | X12: 209785 | Y12: SAN ISIDRO | Z12: 3 NGT | AC12: 3039
A13: CYLINDER WITH REFILL | F13: NONE | H13: NONE | I13: =IF(AND(F13<>"NONE",H13<>"NONE", G13>0),VLOOKUP(H13,$A$52:$B$63,2,FALSE)-G13+VLOOKUP(H13,$A$25:$B$36,2,FALSE),"") | K13: 50KG BLUE | L13: ='DAILY STOCKS (W)'!U13 | M13: 0 | N13: 0 | O13: =C23 -> 0 | P13: =C35 -> 0 | Q13: =COUNTIF($H$3:$H$25,K13) -> 0 | R13: =C47 -> 0 | T13: =L13+M13+N13-O13-P13-Q13-R13-S13 -> 0 | V13: =U13-T13 -> 0 | Z13: 2 PV | AC13: 2026
A14: 2.7KG | B14: =B26+B53 -> 1480 | C14: 0 | D14: =C14*B14 -> 0 | F14: NONE | H14: NONE | I14: =IF(AND(F14<>"NONE",H14<>"NONE", G14>0),VLOOKUP(H14,$A$52:$B$63,2,FALSE)-G14+VLOOKUP(H14,$A$25:$B$36,2,FALSE),"") | K14: 50KG CODED | L14: ='DAILY STOCKS (W)'!U14 -> 5 | M14: 0 | N14: 0 | O14: =C24 -> 0 | P14: =C36 -> 4 | Q14: =COUNTIF($H$3:$H$25,K14) -> 0 | R14: =C48 -> 0 | T14: =L14+M14+N14-O14-P14-Q14-R14-S14 -> 1 | U14: 1 | V14: =U14-T14 -> 0 | X14: 209787 | Y14: BANDOLA | Z14: 1 F2.7KG | AA14: 280
A15: 2.7KG FIESTA | B15: =B27+B54 -> 1480 | C15: 0 | D15: =C15*B15 -> 0 | F15: NONE | H15: NONE | I15: =IF(AND(F15<>"NONE",H15<>"NONE", G15>0),VLOOKUP(H15,$A$52:$B$63,2,FALSE)-G15+VLOOKUP(H15,$A$25:$B$36,2,FALSE),"") | X15: 209788 | Y15: LABIANO | Z15: 1 NGT | AA15: 963 | AB15: 50
A16: 7KG PASAK | B16: =B28+B55 -> 2588 | C16: 0 | D16: =C16*B16 -> 0 | F16: NONE | H16: NONE | I16: =IF(AND(F16<>"NONE",H16<>"NONE", G16>0),VLOOKUP(H16,$A$52:$B$63,2,FALSE)-G16+VLOOKUP(H16,$A$25:$B$36,2,FALSE),"") | X16: 209789 | Y16: QUIDING | Z16: 1 PV | AA16: 938 | AB16: 75
A17: 7KG RUSKAS | B17: =B29+B56 -> 2588 | C17: 0 | D17: =C17*B17 -> 0 | F17: NONE | H17: NONE | I17: =IF(AND(F17<>"NONE",H17<>"NONE", G17>0),VLOOKUP(H17,$A$52:$B$63,2,FALSE)-G17+VLOOKUP(H17,$A$25:$B$36,2,FALSE),"") | K17: EMPTY | L17: BEG | M17: PLANTA | N17: REFILL | O17: SWAP | P17: RETURNED | Q17: END | R17: AUD | S17: VAR | X17: 209790 | Y17: SHAKEYS | Z17: 4 50CODED | AC17: 17836
A18: 11KG PASAK | B18: =B30+B57 -> 3013 | C18: 0 | D18: =C18*B18 -> 0 | F18: NONE | H18: NONE | I18: =IF(AND(F18<>"NONE",H18<>"NONE", G18>0),VLOOKUP(H18,$A$52:$B$63,2,FALSE)-G18+VLOOKUP(H18,$A$25:$B$36,2,FALSE),"") | K18: 2.7KG | L18: ='DAILY STOCKS (W)'!R18 -> 49 | M18: =N4 -> 0 | N18: =P4 -> 5 | O18: =countif($F$3:$F$25,K18) -> 0 | Q18: =L18-M18+N18+O18+P18 -> 54 | R18: 54 | S18: =R18-Q18 -> 0 | X18: 209791 | Y18: LOPEZ | Z18: 1 NGT | AA18: 963 | AB18: 50
A19: 11KG RUSKAS | B19: =B31+B58 -> 3013 | C19: 0 | D19: =C19*B19 -> 0 | F19: NONE | H19: NONE | I19: =IF(AND(F19<>"NONE",H19<>"NONE", G19>0),VLOOKUP(H19,$A$52:$B$63,2,FALSE)-G19+VLOOKUP(H19,$A$25:$B$36,2,FALSE),"") | K19: 2.7KG FIESTA | L19: ='DAILY STOCKS (W)'!R19 -> 10 | M19: =N5 -> 0 | N19: =P5 -> 1 | O19: =countif($F$3:$F$25,K19) -> 0 | Q19: =L19-M19+N19+O19+P19 -> 11 | R19: 11 | S19: =R19-Q19 -> 0 | X19: 209793 | Y19: ALIMAN | Z19: 1 PV | AA19: 963 | AB19: 50
A20: ELITE PASAK | B20: =B32+B59 -> 4738 | C20: 0 | D20: =C20*B20 -> 0 | F20: NONE | H20: NONE | I20: =IF(AND(F20<>"NONE",H20<>"NONE", G20>0),VLOOKUP(H20,$A$52:$B$63,2,FALSE)-G20+VLOOKUP(H20,$A$25:$B$36,2,FALSE),"") | K20: 7KG PASAK | L20: ='DAILY STOCKS (W)'!R20 -> 6 | M20: =N6 -> 0 | N20: =P6 -> 1 | O20: =countif($F$3:$F$25,K20) -> 0 | Q20: =L20-M20+N20+O20+P20 -> 7 | R20: 7 | S20: =R20-Q20 -> 0 | X20: 209794 | Y20: GOMEZ | Z20: 2 PV | AA20: 1926 | AB20: 100
A21: ELITE RUSKAS | B21: =B33+B60 -> 4738 | C21: 0 | D21: =C21*B21 -> 0 | F21: NONE | H21: NONE | I21: =IF(AND(F21<>"NONE",H21<>"NONE", G21>0),VLOOKUP(H21,$A$52:$B$63,2,FALSE)-G21+VLOOKUP(H21,$A$25:$B$36,2,FALSE),"") | K21: 7KG RUSKAS | L21: ='DAILY STOCKS (W)'!R21 -> 26 | M21: =N7 -> 0 | N21: =P7 -> 0 | O21: =countif($F$3:$F$25,K21) -> 0 | Q21: =L21-M21+N21+O21+P21 -> 26 | R21: 26 | S21: =R21-Q21 -> 0 | X21: 209795 | Y21: RAZON | Z21: 1 PV | AA21: 963 | AB21: 50
A22: 22KG | B22: =B34+B61 -> 5665 | C22: 0 | D22: =C22*B22 -> 0 | F22: NONE | H22: NONE | I22: =IF(AND(F22<>"NONE",H22<>"NONE", G22>0),VLOOKUP(H22,$A$52:$B$63,2,FALSE)-G22+VLOOKUP(H22,$A$25:$B$36,2,FALSE),"") | K22: 11KG PASAK | L22: ='DAILY STOCKS (W)'!R22 -> 157 | M22: =N8 -> 5 | N22: =P8 -> 12 | O22: =countif($F$3:$F$25,K22) -> 0 | Q22: =L22-M22+N22+O22+P22 -> 164 | R22: 168 | S22: =R22-Q22 -> 4 | X22: 209797 | Y22: GEMBA | Z22: 1 PV | AA22: 988 | AB22: 25
A23: 50KG BLUE | B23: =B35+B62 -> 9459 | C23: 0 | D23: =C23*B23 -> 0 | F23: NONE | H23: NONE | I23: =IF(AND(F23<>"NONE",H23<>"NONE", G23>0),VLOOKUP(H23,$A$52:$B$63,2,FALSE)-G23+VLOOKUP(H23,$A$25:$B$36,2,FALSE),"") | K23: 11KG RUSKAS | L23: ='DAILY STOCKS (W)'!R23 -> 122 | M23: =N9 -> 2 | N23: =C31 -> 14 | O23: =countif($F$3:$F$25,K23) -> 0 | Q23: =L23-M23+N23+O23+P23 -> 134 | R23: 135 | S23: =R23-Q23 -> 1 | X23: 209798 | Y23: LUZ | Z23: 1 2.7KG | AA23: 280
A24: 50KG CODED | B24: =B36+B63 -> 9459 | C24: 0 | D24: =C24*B24 -> 0 | F24: NONE | H24: NONE | I24: =IF(AND(F24<>"NONE",H24<>"NONE", G24>0),VLOOKUP(H24,$A$52:$B$63,2,FALSE)-G24+VLOOKUP(H24,$A$25:$B$36,2,FALSE),"") | J24: 54 | K24: ELITE PASAK | L24: ='DAILY STOCKS (W)'!R24 -> 2 | M24: =N10 -> 0 | N24: =P10 -> 0 | O24: =countif($F$3:$F$25,K24) -> 0 | Q24: =L24-M24+N24+O24+P24 -> 2 | R24: 2 | S24: =R24-Q24 -> 0 | X24: 209799 | Y24: EMPLOMA | Z24: 1 PV | AA24: 988 | AB24: 25
A25: REFILL | F25: NONE | H25: NONE | I25: =IF(AND(F25<>"NONE",H25<>"NONE", G25>0),VLOOKUP(H25,$A$52:$B$63,2,FALSE)-G25+VLOOKUP(H25,$A$25:$B$36,2,FALSE),"") | K25: ELITE RUSKAS | L25: ='DAILY STOCKS (W)'!R25 -> 59 | M25: =N11 -> 0 | N25: =P11 -> 2 | O25: =countif($F$3:$F$25,K25) -> 0 | Q25: =L25-M25+N25+O25+P25 -> 61 | R25: 61 | S25: =R25-Q25 -> 0 | X25: 209800 | Y25: FRAGATA | Z25: 1 NGT | AA25: 988 | AB25: 25
A26: 2.7KG | B26: 280 | C26: 5 | D26: =C26*B26 -> 1400 | F26: TOTAL SALES | I26: =sum(I3:I25) -> 0 | K26: 22KG | L26: ='DAILY STOCKS (W)'!R26 -> 2 | M26: =N12 -> 0 | N26: =P12 -> 1 | O26: =countif($F$3:$F$25,K26) -> 0 | Q26: =L26-M26+N26+O26+P26 -> 3 | R26: 3 | S26: =R26-Q26 -> 0 | X26: 209961 | Y26: NIDEA | Z26: 1 NGT | AA26: 988 | AB26: 25
A27: 2.7KG FIESTA | B27: 280 | C27: 1 | D27: =C27*B27 -> 280 | K27: 50KG BLUE | L27: ='DAILY STOCKS (W)'!R27 -> 23 | M27: =N13 -> 0 | N27: =P13 -> 0 | O27: =countif($F$3:$F$25,K27) -> 3 | Q27: =L27-M27+N27+O27+P27 -> 26 | R27: 26 | S27: =R27-Q27 -> 0 | X27: 209962 | Y27: PORTADES | Z27: 1 PV ELITE | AA27: 938 | AB27: 100
A28: 7KG PASAK | B28: 688 | C28: 1 | D28: =C28*B28 -> 688 | K28: 50KG CODED | L28: ='DAILY STOCKS (W)'!R28 -> 16 | M28: =N14 -> 0 | N28: =P14 -> 4 | O28: =countif($F$3:$F$25,K28) -> 0 | Q28: =L28-M28+N28+O28+P28 -> 20 | R28: 20 | S28: =R28-Q28 -> 0 | X28: 209963 | Y28: DE LEON | Z28: 1 PV | AA28: 988 | AB28: 25
A29: 7KG RUSKAS | B29: 688 | C29: 0 | D29: =C29*B29 -> 0 | X29: 209964 | Y29: CORECES | Z29: 1 22KG | AA29: 1789 | AB29: 176
A30: 11KG PASAK | B30: 1013 | C30: 12 | D30: =C30*B30 -> 12156 | X30: 209965 | Y30: FEDERIS | Z30: 1 NGT | AA30: 988 | AB30: 25
A31: 11KG RUSKAS | B31: 1013 | C31: 14 | D31: =C31*B31 -> 14182 | K31: ACCESSORIES | L31: BEG | M31: DELIVERY | N31: SOLD | O31: DEFECTIVE | P31: END | Q31: AUD | R31: VAR | X31: 209966 | Y31: DEVERA | Z31: 1 NGT | AA31: 988 | AB31: 25
A32: ELITE PASAK | B32: 1038 | C32: 0 | D32: =C32*B32 -> 0 | K32: REGULATOR | X32: 209967 | Y32: REYES | Z32: 1 2.7KG | AA32: 280
A33: ELITE RUSKAS | B33: 1038 | C33: 2 | D33: =C33*B33 -> 2076 | K33: REGULATOR (PASAK) | L33: ='DAILY STOCKS (W)'!Q33 -> 0 | M33: 0 | N33: =C4 -> 0 | P33: =L33+M33-N33-O33 -> 0 | R33: =Q33-P33 -> 0 | X33: 207881 | Y33: JAY | Z33: 1 2.7KG | AA33: 280
A34: 22KG | B34: 1965 | C34: 1 | D34: =C34*B34 -> 1965 | K34: REGULATOR (RUSKAS) | L34: ='DAILY STOCKS (W)'!Q34 -> 12 | M34: 0 | N34: =C5 -> 0 | P34: =L34+M34-N34-O34 -> 12 | Q34: 12 | R34: =Q34-P34 -> 0 | X34: 209968 | Y34: JAY | Z34: 1 NGT | AA34: 963 | AB34: 50
A35: 50KG BLUE | B35: 4459 | C35: 0 | D35: =C35*B35 -> 0 | K35: OTHERS | X35: 209969 | Y35: HEAVENLY | Z35: 1 PV ELITE | AB35: 100 | AC35: 938
A36: 50KG CODED | B36: 4459 | C36: 4 | D36: =C36*B36 -> 17836 | K36: GS-3 | L36: ='DAILY STOCKS (W)'!Q36 -> 18 | M36: 0 | N36: =C7 -> 0 | P36: =L36+M36-N36-O36 -> 18 | Q36: 18 | R36: =Q36-P36 -> 0
A37: BORROW | K37: HOSE | L37: ='DAILY STOCKS (W)'!Q37 -> 3 | M37: 0 | N37: =C8 -> 0 | P37: =L37+M37-N37-O37 -> 3 | Q37: 3 | R37: =Q37-P37 -> 0
A38: 2.7KG | B38: =B26 -> 280 | C38: 0 | D38: =C38*B38 -> 0 | K38: CLAMP | L38: ='DAILY STOCKS (W)'!Q38 -> 85 | M38: 0 | N38: =C9 -> 0 | P38: =L38+M38-N38-O38 -> 85 | Q38: 85 | R38: =Q38-P38 -> 0
A39: 2.7KG FIESTA | B39: =B27 -> 280 | C39: 0 | D39: =C39*B39 -> 0 | K39: REYNA (SINGLE BURNER) | L39: ='DAILY STOCKS (W)'!Q39 -> 0 | M39: 0 | N39: =C10 -> 0 | P39: =L39+M39-N39-O39 -> 0 | R39: =Q39-P39 -> 0
A40: 7KG PASAK | B40: =B28 -> 688 | C40: 0 | D40: =C40*B40 -> 0 | K40: REYNA (DOUBLE BURNER) | L40: ='DAILY STOCKS (W)'!Q40 -> 0 | M40: 0 | N40: =C11 -> 0 | P40: =L40+M40-N40-O40 -> 0 | R40: =Q40-P40 -> 0
A41: 7KG RUSKAS | B41: =B29 -> 688 | C41: 0 | D41: =C41*B41 -> 0 | K41: Y TYPE | L41: ='DAILY STOCKS (W)'!Q41 -> 3 | M41: 0 | N41: =C12 -> 0 | P41: =L41+M41-N41-O41 -> 3 | Q41: 3 | R41: =Q41-P41 -> 0
A42: 11KG PASAK | B42: =B30 -> 1013 | C42: 0 | D42: =C42*B42 -> 0
A43: 11KG RUSKAS | B43: =B31 -> 1013 | C43: 0 | D43: =C43*B43 -> 0
A44: ELITE PASAK | B44: =B32 -> 1038 | C44: 0 | D44: =C44*B44 -> 0 | K44: TOTAL CYLINDER | L44: BEG | M44: END | N44: VAR
A45: ELITE RUSKAS | B45: =B33 -> 1038 | C45: 0 | D45: =C45*B45 -> 0 | K45: 2.7KG | L45: =L4+L18 -> 67 | M45: =T4+Q18 -> 67 | N45: =M45-L45 -> 0
A46: 22KG | B46: =B34 -> 1965 | C46: 0 | D46: =C46*B46 -> 0 | K46: 2.7KG FIESTA | L46: =L5+L19 -> 18 | M46: =T5+Q19 -> 18 | N46: =M46-L46 -> 0
A47: 50KG BLUE | B47: =B35 -> 4459 | C47: 0 | D47: =C47*B47 -> 0 | K47: 7KG (PASAK) | L47: =L6+L20 -> 19 | M47: =T6+Q20 -> 19 | N47: =M47-L47 -> 0
A48: 50KG CODED | B48: =B36 -> 4459 | C48: 0 | D48: =C48*B48 -> 0 | K48: 7KG (RUSKAS) | L48: =L7+L21 -> 31 | M48: =T7+Q21 -> 31 | N48: =M48-L48 -> 0
A49: TOTAL SALES | D49: =sum(D4:D48) -> 50583 | K49: 11KG (PASAK) | L49: =L8+L22 -> 164 | M49: =T8+Q22 -> 164 | N49: =M49-L49 -> 0
K50: 11KG (RUSKAS) | L50: =L9+L23 -> 148 | M50: =T9+Q23 -> 148 | N50: =M50-L50 -> 0
K51: ELITE (PASAK) | L51: =L10+L24 -> 10 | M51: =T10+Q24 -> 10 | N51: =M51-L51 -> 0
A52: CYLINDER PRICE LIST | B52: PRICE | K52: ELITE (RUSKAS) | L52: =L11+L25 -> 75 | M52: =T11+Q25 -> 75 | N52: =M52-L52 -> 0
A53: 2.7KG | B53: 1200 | K53: 22KG | L53: =L12+L26 -> 6 | M53: =T12+Q26 -> 6 | N53: =M53-L53 -> 0
A54: 2.7KG FIESTA | B54: 1200 | K54: 50KG (BLUE) | L54: =L13+L27 -> 23 | M54: =T13+Q27 -> 26 | N54: =M54-L54 -> 3
A55: 7KG PASAK | B55: 1900 | K55: 50KG (CODED) | L55: =L14+L28 -> 21 | M55: =T14+Q28 -> 21 | N55: =M55-L55 -> 0
A56: 7KG RUSKAS | B56: 1900
A57: 11KG PASAK | B57: 2000
A58: 11KG RUSKAS | B58: 2000 | K58: BORROWED | L58: BEG | M58: BORROWED | N58: RETURNED | O58: END
A59: ELITE PASAK | B59: 3700 | K59: 2.7KG | L59: ='DAILY STOCKS (W)'!O59 -> 0 | M59: =R4 -> 0 | N59: =P18 | O59: =L59+M59-N59 -> 0
A60: ELITE RUSKAS | B60: 3700 | K60: 2.7KG FIESTA | L60: ='DAILY STOCKS (W)'!O60 -> 0 | M60: =R5 -> 0 | N60: =P19 | O60: =L60+M60-N60 -> 0
A61: 22KG | B61: 3700 | K61: 7KG (PASAK) | L61: ='DAILY STOCKS (W)'!O61 -> 0 | M61: =R6 -> 0 | N61: =P20 | O61: =L61+M61-N61 -> 0
A62: 50KG BLUE | B62: 5000 | K62: 7KG (RUSKAS) | L62: ='DAILY STOCKS (W)'!O62 -> 0 | M62: =R7 -> 0 | N62: =P21 | O62: =L62+M62-N62 -> 0
A63: 50KG CODED | B63: 5000 | K63: 11KG (PASAK) | L63: ='DAILY STOCKS (W)'!O63 -> -1 | M63: =R8 -> 0 | N63: =P22 | O63: =L63+M63-N63 -> -1
K64: 11KG (RUSKAS) | L64: ='DAILY STOCKS (W)'!O64 -> 0 | M64: =R9 -> 0 | N64: =P23 | O64: =L64+M64-N64 -> 0
K65: ELITE (PASAK) | L65: ='DAILY STOCKS (W)'!O65 -> 0 | M65: =R10 -> 0 | N65: =P24 | O65: =L65+M65-N65 -> 0
K66: ELITE (RUSKAS) | L66: ='DAILY STOCKS (W)'!O66 -> 0 | M66: =R11 -> 0 | N66: =P25 | O66: =L66+M66-N66 -> 0
K67: 22KG | L67: ='DAILY STOCKS (W)'!O67 -> 0 | M67: =R12 -> 0 | N67: =P26 | O67: =L67+M67-N67 -> 0
K68: 50KG (BLUE) | L68: ='DAILY STOCKS (W)'!O68 -> 0 | M68: =R13 -> 0 | N68: =P27 | O68: =L68+M68-N68 -> 0
K69: 50KG (CODED) | L69: ='DAILY STOCKS (W)'!O69 -> 0 | M69: =R14 -> 0 | N69: =P28 | O69: =L69+M69-N69 -> 0
X105: TOTAL | AA105: =SUM(AA3:AA104) -> 24530 | AB105: =SUM(AB3:AB104) -> 1276 | AC105: =SUM(AC3:AC104) -> 24777 | AD105: =SUM(AD3:AD104) -> 0

Sheet DAILY STOCKS (F)
F1: UPGRADE / SWAP | K1: DAILYSTOCKS MONITORING | X1: DISCOUNTS
A2: PRODUCT NAME | B2: SRP | C2: SOLD | D2: TOTAL SALES | F2: PRODUCT TO SWAP | G2: PURCHASE PRICE | H2: PRODUCT TO BUY | I2: TOTAL SALES | K2: FULL CYLINDER | L2: BEG | M2: PLANTA PURCHASES | N2: PLANTA REFILL | O2: SOLD | P2: REFILL | Q2: SWAP | R2: BORROWED | S2: RETURN | T2: END | U2: AUD | V2: VAR | X2: INVOICE | Y2: NAME | Z2: PARTICULARS | AA2: CASH | AB2: DISCOUNT | AC2: A/R | AD2: AMOUNT
A3: REGULATOR | F3: NONE | G3: 0 | H3: NONE | I3: =IF(AND(F3<>"NONE",H3<>"NONE", G3>0),VLOOKUP(H3,$A$52:$B$63,2,FALSE)-G3+VLOOKUP(H3,$A$25:$B$36,2,FALSE),"") | X3: 209451 | Y3: SALVINO | Z3: 1 PV | AA3: 988 | AB3: 25
A4: REGULATOR (PASAK) | B4: 650 | C4: 0 | D4: =C4*B4 -> 0 | F4: NONE | H4: NONE | I4: =IF(AND(F4<>"NONE",H4<>"NONE", G4>0),VLOOKUP(H4,$A$52:$B$63,2,FALSE)-G4+VLOOKUP(H4,$A$25:$B$36,2,FALSE),"") | K4: 2.7KG | L4: ='DAILY STOCKS (TH)'!U4 -> 13 | M4: 0 | N4: 48 | O4: =C14 -> 0 | P4: =C26 -> 34 | Q4: =COUNTIF($H$3:$H$25,K4) -> 0 | R4: =C38 -> 0 | T4: =L4+M4+N4-O4-P4-Q4-R4-S4 -> 27 | U4: 27 | V4: =U4-T4 -> 0 | X4: 209452 | Y4: JIMENEZ | Z4: 1 NGT | AA4: 963 | AB4: 50
A5: REGULATOR (RUSKAS) | B5: 375 | C5: 1 | D5: =C5*B5 -> 375 | F5: NONE | H5: NONE | I5: =IF(AND(F5<>"NONE",H5<>"NONE", G5>0),VLOOKUP(H5,$A$52:$B$63,2,FALSE)-G5+VLOOKUP(H5,$A$25:$B$36,2,FALSE),"") | K5: 2.7KG FIESTA | L5: ='DAILY STOCKS (TH)'!U5 -> 7 | M5: 0 | N5: 0 | O5: =C15 -> 0 | P5: =C27 -> 1 | Q5: =COUNTIF($H$3:$H$25,K5) -> 0 | R5: =C39 -> 0 | T5: =L5+M5+N5-O5-P5-Q5-R5-S5 -> 6 | U5: 6 | V5: =U5-T5 -> 0 | X5: 209453 | Y5: JAZARENO | Z5: 1 PV | AA5: 938 | AB5: 75
A6: OTHERS | F6: NONE | H6: NONE | I6: =IF(AND(F6<>"NONE",H6<>"NONE", G6>0),VLOOKUP(H6,$A$52:$B$63,2,FALSE)-G6+VLOOKUP(H6,$A$25:$B$36,2,FALSE),"") | K6: 7KG PASAK | L6: ='DAILY STOCKS (TH)'!U6 -> 12 | M6: 0 | N6: 0 | O6: =C16 -> 0 | P6: =C28 -> 3 | Q6: =COUNTIF($H$3:$H$25,K6) -> 0 | R6: =C40 -> 0 | T6: =L6+M6+N6-O6-P6-Q6-R6-S6 -> 9 | U6: 9 | V6: =U6-T6 -> 0 | X6: 209454 | Y6: MALHEYS | Z6: 1 NGT | AA6: 938 | AB6: 75
A7: GS-3 | B7: 650 | C7: 0 | D7: =C7*B7 -> 0 | F7: NONE | H7: NONE | I7: =IF(AND(F7<>"NONE",H7<>"NONE", G7>0),VLOOKUP(H7,$A$52:$B$63,2,FALSE)-G7+VLOOKUP(H7,$A$25:$B$36,2,FALSE),"") | K7: 7KG RUSKAS | L7: ='DAILY STOCKS (TH)'!U7 -> 5 | M7: 0 | N7: 15 | O7: =C17 -> 0 | P7: =C29 -> 3 | Q7: =COUNTIF($H$3:$H$25,K7) -> 0 | R7: =C41 -> 0 | T7: =L7+M7+N7-O7-P7-Q7-R7-S7 -> 17 | U7: 17 | V7: =U7-T7 -> 0 | X7: 209455 | Y7: CADLAN | Z7: 8 PV | AC7: 8104
A8: HOSE | B8: 180 | C8: 1 | D8: =C8*B8 -> 180 | F8: NONE | H8: NONE | I8: =IF(AND(F8<>"NONE",H8<>"NONE", G8>0),VLOOKUP(H8,$A$52:$B$63,2,FALSE)-G8+VLOOKUP(H8,$A$25:$B$36,2,FALSE),"") | K8: 11KG PASAK | L8: ='DAILY STOCKS (TH)'!U8 -> 0 | M8: 0 | N8: 105 | O8: =C18 -> 0 | P8: =C30 -> 83 | Q8: =COUNTIF($H$3:$H$25,K8) -> 0 | R8: =C42 -> 0 | S8: 3 | T8: =L8+M8+N8-O8-P8-Q8-R8-S8 -> 19 | U8: 19 | V8: =U8-T8 -> 0 | Z8: 5 2.7KG | AC8: 1400
A9: CLAMP | B9: 20 | C9: 1 | D9: =C9*B9 -> 20 | F9: NONE | H9: NONE | I9: =IF(AND(F9<>"NONE",H9<>"NONE", G9>0),VLOOKUP(H9,$A$52:$B$63,2,FALSE)-G9+VLOOKUP(H9,$A$25:$B$36,2,FALSE),"") | K9: 11KG RUSKAS | L9: ='DAILY STOCKS (TH)'!U9 -> 15 | M9: 0 | N9: 105 | O9: =C19 -> 1 | P9: =C31 -> 87 | Q9: =COUNTIF($H$3:$H$25,K9) -> 0 | R9: =C43 -> 0 | S9: 9 | T9: =L9+M9+N9-O9-P9-Q9-R9-S9 -> 23 | U9: 23 | V9: =U9-T9 -> 0 | Z9: 6 NGT | AC9: 6078
A10: REYNA (SINGLE BURNER) | B10: 650 | C10: 0 | D10: =C10*B10 -> 0 | F10: NONE | H10: NONE | I10: =IF(AND(F10<>"NONE",H10<>"NONE", G10>0),VLOOKUP(H10,$A$52:$B$63,2,FALSE)-G10+VLOOKUP(H10,$A$25:$B$36,2,FALSE),"") | K10: ELITE PASAK | L10: ='DAILY STOCKS (TH)'!U10 -> 8 | M10: 0 | N10: 0 | O10: =C20 -> 0 | P10: =C32 -> 0 | Q10: =COUNTIF($H$3:$H$25,K10) -> 0 | R10: =C44 -> 0 | T10: =L10+M10+N10-O10-P10-Q10-R10-S10 -> 8 | U10: 8 | V10: =U10-T10 -> 0 | X10: 209456 | Y10: VELASCO | Z10: 1 NGT | AA10: 963 | AB10: 50
A11: REYNA (DOUBLE BURNER) | B11: 1200 | C11: 0 | D11: =C11*B11 -> 0 | F11: NONE | H11: NONE | I11: =IF(AND(F11<>"NONE",H11<>"NONE", G11>0),VLOOKUP(H11,$A$52:$B$63,2,FALSE)-G11+VLOOKUP(H11,$A$25:$B$36,2,FALSE),"") | K11: ELITE RUSKAS | L11: ='DAILY STOCKS (TH)'!U11 -> 14 | M11: 0 | N11: 0 | O11: =C21 -> 0 | P11: =C33 -> 3 | Q11: =COUNTIF($H$3:$H$25,K11) -> 0 | R11: =C45 -> 0 | T11: =L11+M11+N11-O11-P11-Q11-R11-S11 -> 11 | U11: 11 | V11: =U11-T11 -> 0 | X11: 209457 | Y11: SAN ISIDRO | Z11: 3 PV | AC11: 3039
A12: Y TYPE | B12: 150 | C12: 0 | D12: =C12*B12 -> 0 | F12: NONE | H12: NONE | I12: =IF(AND(F12<>"NONE",H12<>"NONE", G12>0),VLOOKUP(H12,$A$52:$B$63,2,FALSE)-G12+VLOOKUP(H12,$A$25:$B$36,2,FALSE),"") | K12: 22KG | L12: ='DAILY STOCKS (TH)'!U12 -> 3 | M12: 0 | N12: 0 | O12: =C22 -> 0 | P12: =C34 -> 0 | Q12: =COUNTIF($H$3:$H$25,K12) -> 0 | R12: =C46 -> 0 | T12: =L12+M12+N12-O12-P12-Q12-R12-S12 -> 3 | U12: 3 | V12: =U12-T12 -> 0 | Z12: 2 NGT | AC12: 2026
A13: CYLINDER WITH REFILL | F13: NONE | H13: NONE | I13: =IF(AND(F13<>"NONE",H13<>"NONE", G13>0),VLOOKUP(H13,$A$52:$B$63,2,FALSE)-G13+VLOOKUP(H13,$A$25:$B$36,2,FALSE),"") | K13: 50KG BLUE | L13: ='DAILY STOCKS (TH)'!U13 | M13: 0 | N13: 0 | O13: =C23 -> 0 | P13: =C35 -> 0 | Q13: =COUNTIF($H$3:$H$25,K13) -> 0 | R13: =C47 -> 0 | T13: =L13+M13+N13-O13-P13-Q13-R13-S13 -> 0 | V13: =U13-T13 -> 0 | X13: 209458 | Y13: HONDA | Z13: 1 PV | AB13: 75 | AC13: 938
A14: 2.7KG | B14: =B26+B53 -> 1480 | C14: 0 | D14: =C14*B14 -> 0 | F14: NONE | H14: NONE | I14: =IF(AND(F14<>"NONE",H14<>"NONE", G14>0),VLOOKUP(H14,$A$52:$B$63,2,FALSE)-G14+VLOOKUP(H14,$A$25:$B$36,2,FALSE),"") | K14: 50KG CODED | L14: ='DAILY STOCKS (TH)'!U14 -> 1 | M14: 0 | N14: 10 | O14: =C24 -> 0 | P14: =C36 -> 7 | Q14: =COUNTIF($H$3:$H$25,K14) -> 0 | R14: =C48 -> 0 | T14: =L14+M14+N14-O14-P14-Q14-R14-S14 -> 4 | U14: 4 | V14: =U14-T14 -> 0 | X14: 209459 | Y14: CBSUA | Z14: 1 PV | AA14: 938 | AB14: 75
A15: 2.7KG FIESTA | B15: =B27+B54 -> 1480 | C15: 0 | D15: =C15*B15 -> 0 | F15: NONE | H15: NONE | I15: =IF(AND(F15<>"NONE",H15<>"NONE", G15>0),VLOOKUP(H15,$A$52:$B$63,2,FALSE)-G15+VLOOKUP(H15,$A$25:$B$36,2,FALSE),"") | X15: 209460 | Y15: VALIENTE | Z15: 1 NGT | AA15: 963 | AB15: 50
A16: 7KG PASAK | B16: =B28+B55 -> 2588 | C16: 0 | D16: =C16*B16 -> 0 | F16: NONE | H16: NONE | I16: =IF(AND(F16<>"NONE",H16<>"NONE", G16>0),VLOOKUP(H16,$A$52:$B$63,2,FALSE)-G16+VLOOKUP(H16,$A$25:$B$36,2,FALSE),"") | X16: 209461 | Y16: JAZARENO | Z16: 1PV | AA16: 938 | AB16: 75
A17: 7KG RUSKAS | B17: =B29+B56 -> 2588 | C17: 0 | D17: =C17*B17 -> 0 | F17: NONE | H17: NONE | I17: =IF(AND(F17<>"NONE",H17<>"NONE", G17>0),VLOOKUP(H17,$A$52:$B$63,2,FALSE)-G17+VLOOKUP(H17,$A$25:$B$36,2,FALSE),"") | K17: EMPTY | L17: BEG | M17: PLANTA | N17: REFILL | O17: SWAP | P17: RETURNED | Q17: END | R17: AUD | S17: VAR | X17: 209462 | Y17: ABONITA | Z17: 1 NGT | AA17: 963 | AB17: 50
A18: 11KG PASAK | B18: =B30+B57 -> 3013 | C18: 0 | D18: =C18*B18 -> 0 | F18: NONE | H18: NONE | I18: =IF(AND(F18<>"NONE",H18<>"NONE", G18>0),VLOOKUP(H18,$A$52:$B$63,2,FALSE)-G18+VLOOKUP(H18,$A$25:$B$36,2,FALSE),"") | K18: 2.7KG | L18: ='DAILY STOCKS (TH)'!R18 -> 54 | M18: =N4 -> 48 | N18: =P4 -> 34 | O18: =countif($F$3:$F$25,K18) -> 0 | Q18: =L18-M18+N18+O18+P18 -> 40 | R18: 41 | S18: =R18-Q18 -> 1 | X18: 209463 | Y18: ORDIZ | Z18: 5 NGT | AA18: 4690 | AB18: 375
A19: 11KG RUSKAS | B19: =B31+B58 -> 3013 | C19: 1 | D19: =C19*B19 -> 3013 | F19: NONE | H19: NONE | I19: =IF(AND(F19<>"NONE",H19<>"NONE", G19>0),VLOOKUP(H19,$A$52:$B$63,2,FALSE)-G19+VLOOKUP(H19,$A$25:$B$36,2,FALSE),"") | K19: 2.7KG FIESTA | L19: ='DAILY STOCKS (TH)'!R19 -> 11 | M19: =N5 -> 0 | N19: =P5 -> 1 | O19: =countif($F$3:$F$25,K19) -> 0 | Q19: =L19-M19+N19+O19+P19 -> 12 | R19: 11 | S19: =R19-Q19 -> -1 | X19: 209464 | Y19: SERRANO | Z19: 1 PV | AA19: 963 | AB19: 50
A20: ELITE PASAK | B20: =B32+B59 -> 4738 | C20: 0 | D20: =C20*B20 -> 0 | F20: NONE | H20: NONE | I20: =IF(AND(F20<>"NONE",H20<>"NONE", G20>0),VLOOKUP(H20,$A$52:$B$63,2,FALSE)-G20+VLOOKUP(H20,$A$25:$B$36,2,FALSE),"") | K20: 7KG PASAK | L20: ='DAILY STOCKS (TH)'!R20 -> 7 | M20: =N6 -> 0 | N20: =P6 -> 3 | O20: =countif($F$3:$F$25,K20) -> 0 | Q20: =L20-M20+N20+O20+P20 -> 10 | R20: 10 | S20: =R20-Q20 -> 0 | X20: 209465 | Y20: PILI PETRON M.Z | Z20: 10 NGT | AB20: 1000 | AC20: 9130
A21: ELITE RUSKAS | B21: =B33+B60 -> 4738 | C21: 0 | D21: =C21*B21 -> 0 | F21: NONE | H21: NONE | I21: =IF(AND(F21<>"NONE",H21<>"NONE", G21>0),VLOOKUP(H21,$A$52:$B$63,2,FALSE)-G21+VLOOKUP(H21,$A$25:$B$36,2,FALSE),"") | K21: 7KG RUSKAS | L21: ='DAILY STOCKS (TH)'!R21 -> 26 | M21: =N7 -> 15 | N21: =P7 -> 3 | O21: =countif($F$3:$F$25,K21) -> 0 | Q21: =L21-M21+N21+O21+P21 -> 14 | R21: 14 | S21: =R21-Q21 -> 0 | Z21: 10 PV | AB21: 1000 | AC21: 9130
A22: 22KG | B22: =B34+B61 -> 5665 | C22: 0 | D22: =C22*B22 -> 0 | F22: NONE | H22: NONE | I22: =IF(AND(F22<>"NONE",H22<>"NONE", G22>0),VLOOKUP(H22,$A$52:$B$63,2,FALSE)-G22+VLOOKUP(H22,$A$25:$B$36,2,FALSE),"") | K22: 11KG PASAK | L22: ='DAILY STOCKS (TH)'!R22 -> 168 | M22: =N8 -> 105 | N22: =P8 -> 83 | O22: =countif($F$3:$F$25,K22) -> 0 | Q22: =L22-M22+N22+O22+P22 -> 146 | R22: 146 | S22: =R22-Q22 -> 0 | X22: 209466 | Y22: BAJAR | Z22: 5 NGT | AA22: 4475 | AB22: 590
A23: 50KG BLUE | B23: =B35+B62 -> 9459 | C23: 0 | D23: =C23*B23 -> 0 | F23: NONE | H23: NONE | I23: =IF(AND(F23<>"NONE",H23<>"NONE", G23>0),VLOOKUP(H23,$A$52:$B$63,2,FALSE)-G23+VLOOKUP(H23,$A$25:$B$36,2,FALSE),"") | K23: 11KG RUSKAS | L23: ='DAILY STOCKS (TH)'!R23 -> 135 | M23: =N9 -> 105 | N23: =C31 -> 87 | O23: =countif($F$3:$F$25,K23) -> 0 | Q23: =L23-M23+N23+O23+P23 -> 117 | R23: 117 | S23: =R23-Q23 -> 0 | Z23: 5 PV | AA23: 4475 | AB23: 590
A24: 50KG CODED | B24: =B36+B63 -> 9459 | C24: 0 | D24: =C24*B24 -> 0 | F24: NONE | H24: NONE | I24: =IF(AND(F24<>"NONE",H24<>"NONE", G24>0),VLOOKUP(H24,$A$52:$B$63,2,FALSE)-G24+VLOOKUP(H24,$A$25:$B$36,2,FALSE),"") | K24: ELITE PASAK | L24: ='DAILY STOCKS (TH)'!R24 -> 2 | M24: =N10 -> 0 | N24: =P10 -> 0 | O24: =countif($F$3:$F$25,K24) -> 0 | Q24: =L24-M24+N24+O24+P24 -> 2 | R24: 2 | S24: =R24-Q24 -> 0 | Z24: 1 7KG PV | AA24: 648 | AB24: 40
A25: REFILL | F25: NONE | H25: NONE | I25: =IF(AND(F25<>"NONE",H25<>"NONE", G25>0),VLOOKUP(H25,$A$52:$B$63,2,FALSE)-G25+VLOOKUP(H25,$A$25:$B$36,2,FALSE),"") | K25: ELITE RUSKAS | L25: ='DAILY STOCKS (TH)'!R25 -> 61 | M25: =N11 -> 0 | N25: =P11 -> 3 | O25: =countif($F$3:$F$25,K25) -> 0 | Q25: =L25-M25+N25+O25+P25 -> 64 | R25: 64 | S25: =R25-Q25 -> 0 | Z25: 1 7KG NGT | AA25: 648 | AB25: 40
A26: 2.7KG | B26: 280 | C26: 34 | D26: =C26*B26 -> 9520 | F26: TOTAL SALES | I26: =sum(I3:I25) -> 0 | K26: 22KG | L26: ='DAILY STOCKS (TH)'!R26 -> 3 | M26: =N12 -> 0 | N26: =P12 -> 0 | O26: =countif($F$3:$F$25,K26) -> 0 | Q26: =L26-M26+N26+O26+P26 -> 3 | R26: 3 | S26: =R26-Q26 -> 0 | X26: 209467 | Y26: BALISORO | Z26: 1 NGT | AA26: 963 | AB26: 50
A27: 2.7KG FIESTA | B27: 280 | C27: 1 | D27: =C27*B27 -> 280 | K27: 50KG BLUE | L27: ='DAILY STOCKS (TH)'!R27 -> 26 | M27: =N13 -> 0 | N27: =P13 -> 0 | O27: =countif($F$3:$F$25,K27) -> 0 | Q27: =L27-M27+N27+O27+P27 -> 26 | R27: 31 | S27: =R27-Q27 -> 5 | X27: 209468 | Y27: SAN ISIDRO | Z27: 6 PV | AC27: 6078
A28: 7KG PASAK | B28: 688 | C28: 3 | D28: =C28*B28 -> 2064 | K28: 50KG CODED | L28: ='DAILY STOCKS (TH)'!R28 -> 20 | M28: =N14 -> 10 | N28: =P14 -> 7 | O28: =countif($F$3:$F$25,K28) -> 0 | Q28: =L28-M28+N28+O28+P28 -> 17 | R28: 12 | S28: =R28-Q28 -> -5 | Z28: 1 NGT | AC28: 1013
A29: 7KG RUSKAS | B29: 688 | C29: 3 | D29: =C29*B29 -> 2064 | X29: 209469 | Y29: MANCITA | Z29: 1 PV | AA29: 963 | AB29: 50
A30: 11KG PASAK | B30: 1013 | C30: 83 | D30: =C30*B30 -> 84079 | X30: 209470 | Y30: PITIL | Z30: 1 PV CYL. DEP | AA30: 2000
A31: 11KG RUSKAS | B31: 1013 | C31: 87 | D31: =C31*B31 -> 88131 | K31: ACCESSORIES | L31: BEG | M31: DELIVERY | N31: SOLD | O31: DEFECTIVE | P31: END | Q31: AUD | R31: VAR | Z31: 1 PV | AA31: 963 | AB31: 50
A32: ELITE PASAK | B32: 1038 | C32: 0 | D32: =C32*B32 -> 0 | K32: REGULATOR | Z32: 1 M.REG | AA32: 375
A33: ELITE RUSKAS | B33: 1038 | C33: 3 | D33: =C33*B33 -> 3114 | K33: REGULATOR (PASAK) | L33: ='DAILY STOCKS (TH)'!Q33 | M33: 0 | N33: =C4 -> 0 | P33: =L33+M33-N33-O33 -> 0 | R33: =Q33-P33 -> 0 | Z33: 1 HOSE | AA33: 180
A34: 22KG | B34: 1965 | C34: 0 | D34: =C34*B34 -> 0 | K34: REGULATOR (RUSKAS) | L34: ='DAILY STOCKS (TH)'!Q34 -> 12 | M34: 0 | N34: =C5 -> 1 | P34: =L34+M34-N34-O34 -> 11 | Q34: 11 | R34: =Q34-P34 -> 0 | Z34: 1 CLAMP | AA34: 20
A35: 50KG BLUE | B35: 4459 | C35: 0 | D35: =C35*B35 -> 0 | K35: OTHERS | X35: 209471 | Y35: HEAVENLY | Z35: 1 PV ELITE | AA35: 938 | AB35: 100
A36: 50KG CODED | B36: 4459 | C36: 7 | D36: =C36*B36 -> 31213 | K36: GS-3 | L36: ='DAILY STOCKS (TH)'!Q36 -> 18 | M36: 0 | N36: =C7 -> 0 | P36: =L36+M36-N36-O36 -> 18 | Q36: 18 | R36: =Q36-P36 -> 0 | X36: 209474 | Y36: P. NAGA | Z36: 5 CODED | AB36: 2000 | AC36: 20295
A37: BORROW | K37: HOSE | L37: ='DAILY STOCKS (TH)'!Q37 -> 3 | M37: 0 | N37: =C8 -> 1 | P37: =L37+M37-N37-O37 -> 2 | Q37: 2 | R37: =Q37-P37 -> 0 | Z37: 3 NGT | AB37: 225 | AC37: 2814
A38: 2.7KG | B38: =B26 -> 280 | C38: 0 | D38: =C38*B38 -> 0 | K38: CLAMP | L38: ='DAILY STOCKS (TH)'!Q38 -> 85 | M38: 0 | N38: =C9 -> 1 | P38: =L38+M38-N38-O38 -> 84 | Q38: 84 | R38: =Q38-P38 -> 0 | Z38: 3 PV | AB38: 225 | AC38: 2814
A39: 2.7KG FIESTA | B39: =B27 -> 280 | C39: 0 | D39: =C39*B39 -> 0 | K39: REYNA (SINGLE BURNER) | L39: ='DAILY STOCKS (TH)'!Q39 | M39: 0 | N39: =C10 -> 0 | P39: =L39+M39-N39-O39 -> 0 | R39: =Q39-P39 -> 0 | Z39: 10 2.7KG | AB39: 120 | AC39: 2680
A40: 7KG PASAK | B40: =B28 -> 688 | C40: 0 | D40: =C40*B40 -> 0 | K40: REYNA (DOUBLE BURNER) | L40: ='DAILY STOCKS (TH)'!Q40 | M40: 0 | N40: =C11 -> 0 | P40: =L40+M40-N40-O40 -> 0 | R40: =Q40-P40 -> 0 | X40: 209475 | Y40: P.DEL ROSARIO | Z40: 5 NGT | AB40: 375 | AC40: 4690
A41: 7KG RUSKAS | B41: =B29 -> 688 | C41: 0 | D41: =C41*B41 -> 0 | K41: Y TYPE | L41: ='DAILY STOCKS (TH)'!Q41 -> 3 | M41: 0 | N41: =C12 -> 0 | R41: =Q41-P41 -> 0 | Z41: 5 PV | AB41: 375 | AC41: 4690
A42: 11KG PASAK | B42: =B30 -> 1013 | C42: 0 | D42: =C42*B42 -> 0 | Z42: 5 2.7KG | AB42: 60 | AC42: 1340
A43: 11KG RUSKAS | B43: =B31 -> 1013 | C43: 0 | D43: =C43*B43 -> 0 | X43: 209476 | Y43: FULLERO | Z43: 4 PV | AA43: 3752 | AB43: 300
A44: ELITE PASAK | B44: =B32 -> 1038 | C44: 0 | D44: =C44*B44 -> 0 | K44: TOTAL CYLINDER | L44: BEG | M44: END | N44: VAR | O44: COMMENTS | Z44: 1 NGT | AA44: 938 | AB44: 75
A45: ELITE RUSKAS | B45: =B33 -> 1038 | C45: 0 | D45: =C45*B45 -> 0 | K45: 2.7KG | L45: =L4+L18 -> 67 | M45: =T4+Q18 -> 67 | N45: =M45-L45 -> 0 | X45: 209477 | Y45: BNG | Z45: 1 5OKG CODED | AB45: 400 | AC45: 4059
A46: 22KG | B46: =B34 -> 1965 | C46: 0 | D46: =C46*B46 -> 0 | K46: 2.7KG FIESTA | L46: =L5+L19 -> 18 | M46: =T5+Q19 -> 18 | N46: =M46-L46 -> 0 | Z46: 2 PV ELITE | AB46: 150 | AC46: 1926
A47: 50KG BLUE | B47: =B35 -> 4459 | C47: 0 | D47: =C47*B47 -> 0 | K47: 7KG (PASAK) | L47: =L6+L20 -> 19 | M47: =T6+Q20 -> 19 | N47: =M47-L47 -> 0 | Z47: 2 PV | AB47: 150 | AC47: 1876
A48: 50KG CODED | B48: =B36 -> 4459 | C48: 0 | D48: =C48*B48 -> 0 | K48: 7KG (RUSKAS) | L48: =L7+L21 -> 31 | M48: =T7+Q21 -> 31 | N48: =M48-L48 -> 0 | Z48: 5 NGT | AB48: 375 | AC48: 4690
A49: TOTAL SALES | D49: =sum(D4:D48) -> 224053 | K49: 11KG (PASAK) | L49: =L8+L22 -> 168 | M49: =T8+Q22 -> 165 | N49: =M49-L49 -> -3 | O49: NEGATIVE,BINALIK SA STORE | Z49: 4 2.7KG | AB49: 48 | AC49: 1072
K50: 11KG (RUSKAS) | L50: =L9+L23 -> 150 | M50: =T9+Q23 -> 140 | N50: =M50-L50 -> -10 | O50: NEGATIVE,BINALIK SA STORE | X50: 209479 | Y50: ARCE | Z50: 1 7KG NGT | AA50: 667 | AB50: 21
K51: ELITE (PASAK) | L51: =L10+L24 -> 10 | M51: =T10+Q24 -> 10 | N51: =M51-L51 -> 0 | Z51: 6 2.7KG | AA51: 259 | AB51: 126 | AC51: 1295
A52: CYLINDER PRICE LIST | B52: PRICE | K52: ELITE (RUSKAS) | L52: =L11+L25 -> 75 | M52: =T11+Q25 -> 75 | N52: =M52-L52 -> 0 | Z52: 5 NGT | AA52: 4475 | AB52: 590
A53: 2.7KG | B53: 1200 | K53: 22KG | L53: =L12+L26 -> 6 | M53: =T12+Q26 -> 6 | N53: =M53-L53 -> 0 | Z53: 5 PV | AA53: 4475 | AB53: 590
A54: 2.7KG FIESTA | B54: 1200 | K54: 50KG (BLUE) | L54: =L13+L27 -> 26 | M54: =T13+Q27 -> 26 | N54: =M54-L54 -> 0 | X54: 209480 | Y54: MANUEL | Z54: 1 2.7KG | AA54: 280
A55: 7KG PASAK | B55: 1900 | K55: 50KG (CODED) | L55: =L14+L28 -> 21 | M55: =T14+Q28 -> 21 | N55: =M55-L55 -> 0 | X55: 209481 | Y55: HERNANDEZ | Z55: 1 2.7KG | AA55: 280
A56: 7KG RUSKAS | B56: 1900 | X56: 209482 | Y56: BUNAD | Z56: 1 NGT | AA56: 963 | AB56: 50
A57: 11KG PASAK | B57: 2000 | X57: 209483 | Y57: PADERNAS | Z57: 1 NGT | AA57: 988 | AB57: 25
A58: 11KG RUSKAS | B58: 2000 | K58: BORROWED | L58: BEG | M58: BORROWED | N58: RETURNED | O58: END | X58: 209484 | Y58: PILAPIL | Z58: 1 PV | AA58: 938 | AB58: 75
A59: ELITE PASAK | B59: 3700 | K59: 2.7KG | L59: ='DAILY STOCKS (TH)'!O59 -> 0 | M59: =R4 -> 0 | N59: =P18 | O59: =L59+M59-N59 -> 0 | Z59: 3 NGT | AA59: 2814 | AB59: 225
A60: ELITE RUSKAS | B60: 3700 | K60: 2.7KG FIESTA | L60: ='DAILY STOCKS (TH)'!O60 -> 0 | M60: =R5 -> 0 | N60: =P19 | O60: =L60+M60-N60 -> 0 | X60: 209485 | Y60: ORONAN | Z60: 1 PV | AA60: 963 | AB60: 50
A61: 22KG | B61: 3700 | K61: 7KG (PASAK) | L61: ='DAILY STOCKS (TH)'!O61 -> 0 | M61: =R6 -> 0 | N61: =P20 | O61: =L61+M61-N61 -> 0 | X61: 209486 | Y61: SAN ISIDRO | Z61: 2 NGT | AC61: 2026
A62: 50KG BLUE | B62: 5000 | K62: 7KG (RUSKAS) | L62: ='DAILY STOCKS (TH)'!O62 -> 0 | M62: =R7 -> 0 | N62: =P21 | O62: =L62+M62-N62 -> 0 | Z62: 2 PV | AC62: 2026
A63: 50KG CODED | B63: 5000 | K63: 11KG (PASAK) | L63: ='DAILY STOCKS (TH)'!O63 -> -1 | M63: =R8 -> 0 | N63: =P22 | O63: =L63+M63-N63 -> -1 | X63: 209487 | Y63: ALLARE | Z63: 1 7KG PV | AA63: 688
K64: 11KG (RUSKAS) | L64: ='DAILY STOCKS (TH)'!O64 -> 0 | M64: =R9 -> 0 | N64: =P23 | O64: =L64+M64-N64 -> 0 | X64: 209488 | Y64: BRIOZO | Z64: 1 7KG PV | AA64: 688
K65: ELITE (PASAK) | L65: ='DAILY STOCKS (TH)'!O65 -> 0 | M65: =R10 -> 0 | N65: =P24 | O65: =L65+M65-N65 -> 0 | X65: 209489 | Y65: SAN ISIDRO | Z65: 2 PV | AC65: 2026
K66: ELITE (RUSKAS) | L66: ='DAILY STOCKS (TH)'!O66 -> 0 | M66: =R11 -> 0 | N66: =P25 | O66: =L66+M66-N66 -> 0 | Z66: 1 NGT | AC66: 1013
K67: 22KG | L67: ='DAILY STOCKS (TH)'!O67 -> 0 | M67: =R12 -> 0 | N67: =P26 | O67: =L67+M67-N67 -> 0 | X67: 209490 | Y67: CADLAN | Z67: 5 PV | AC67: 5065
K68: 50KG (BLUE) | L68: ='DAILY STOCKS (TH)'!O68 -> 0 | M68: =R13 -> 0 | N68: =P27 | O68: =L68+M68-N68 -> 0 | Z68: 2 NGT | AC68: 2026
K69: 50KG (CODED) | L69: ='DAILY STOCKS (TH)'!O69 -> 0 | M69: =R14 -> 0 | N69: =P28 | O69: =L69+M69-N69 -> 0 | X69: 209491 | Y69: MATEO | Z69: 1 NGT | AA69: 988 | AB69: 25
X70: 209492 | Y70: URRENTE | Z70: 1 PV | AA70: 938 | AB70: 75
X71: 209493 | Y71: ROMBANO | Z71: 1 PV | AA71: 988 | AB71: 25
X72: 209494 | Y72: FLORECE | Z72: 1 PV | AA72: 988 | AB72: 25
X73: 209495 | Y73: MIRANDA | Z73: 1 2.7KG FIESTA | AA73: 280
X74: 209496 | Y74: REYA | Z74: 1 PV | AA74: 963 | AB74: 50
X75: 209497 | Y75: GARCIA | Z75: 1 PV | AA75: 963 | AB75: 50
X76: 209498 | Y76: SENDICO | Z76: 1 NGT | AA76: 963 | AB76: 50
X77: 209499 | Y77: GUERELLA | Z77: 1 NGT | AA77: 988 | AB77: 25
X78: 207905 | Y78: SANGAY | Z78: 5 NGT | AB78: 375 | AC78: 4690
Z79: 5 PV | AB79: 375 | AC79: 4690
X80: 207906 | Y80: TIGAON | Z80: 2 2.7KG | AB80: 24 | AC80: 536
Z81: 1 7NGT | AB81: 21 | AC81: 667
Z82: 5 NGT | AB82: 375 | AC82: 4690
Z83: 5 PV | AB83: 375 | AC83: 4690
X84: 207909 | Y84: TIMOLA | Z84: 1 PV | AA84: 938 | AB84: 75
Z85: 1 50CODED | AA85: 4059 | AB85: 400
X86: 207910 | Y86: TIMOLA | Z86: 1 PV | AA86: 938 | AB86: 75
X87: 207911 | Y87: CAPARAS | Z87: 1 NGT | AA87: 963 | AB87: 50
X88: 207912 | Y88: DELO SANTOS | Z88: 1 NGT | AA88: 963 | AB88: 50
X89: 207913 | Y89: GUADALUPE | Z89: 1 NGT | AA89: 963 | AB89: 50
X90: 207914 | Y90: ALMASAN | Z90: 1 NGT | AA90: 963 | AB90: 50
X91: 207915 | Y91: DEL JUANA | Z91: 1 NGT | AA91: 963 | AB91: 50
X92: 209472 | Y92: RMN | Z92: 1 NGT | AA92: 938 | AB92: 75
X93: 209473 | Y93: BRIONES | Z93: 1 PV | AA93: 963 | AB93: 50
X105: TOTAL | AA105: =SUM(AA3:AA104) -> 74771 | AB105: =SUM(AB3:AB104) -> 13960 | AC105: =SUM(AC3:AC104) -> 135322 | AD105: =SUM(AD3:AD104) -> 0

Sheet DAILY STOCKS (SAT)
F1: UPGRADE / SWAP | K1: DAILYSTOCKS MONITORING | X1: DISCOUNTS
A2: PRODUCT NAME | B2: SRP | C2: SOLD | D2: TOTAL SALES | F2: PRODUCT TO SWAP | G2: PURCHASE PRICE | H2: PRODUCT TO BUY | I2: TOTAL SALES | K2: FULL CYLINDER | L2: BEG | M2: PLANTA PURCHASES | N2: PLANTA REFILL | O2: SOLD | P2: REFILL | Q2: SWAP | R2: BORROWED | S2: RETURN | T2: END | U2: AUD | V2: VAR | X2: INVOICE | Y2: NAME | Z2: PARTICULARS | AA2: CASH | AB2: DISCOUNT | AC2: A/R | AD2: AMOUNT
A3: REGULATOR | F3: NONE | H3: NONE | I3: =IF(AND(F3<>"NONE",H3<>"NONE", G3>0),VLOOKUP(H3,$A$52:$B$63,2,FALSE)-G3+VLOOKUP(H3,$A$25:$B$36,2,FALSE),"") | X3: 207801 | Y3: LOTIVO | Z3: 1 2.7KG | AA3: 280
A4: REGULATOR (PASAK) | B4: 650 | C4: 0 | D4: =C4*B4 -> 0 | F4: NONE | H4: NONE | I4: =IF(AND(F4<>"NONE",H4<>"NONE", G4>0),VLOOKUP(H4,$A$52:$B$63,2,FALSE)-G4+VLOOKUP(H4,$A$25:$B$36,2,FALSE),"") | K4: 2.7KG | L4: ='DAILY STOCKS (F)'!U4 -> 27 | M4: 0 | N4: 0 | O4: =C14 -> 0 | P4: =C26 -> 9 | Q4: =COUNTIF($H$3:$H$25,K4) -> 0 | R4: =C38 -> 0 | T4: =L4+M4+N4-O4-P4-Q4-R4-S4 -> 18 | U4: 18 | V4: =U4-T4 -> 0 | X4: 207802 | Y4: CORECES | Z4: 1 2.7KG | AA4: 1789 | AB4: 176
A5: REGULATOR (RUSKAS) | B5: 375 | C5: 0 | D5: =C5*B5 -> 0 | F5: NONE | H5: NONE | I5: =IF(AND(F5<>"NONE",H5<>"NONE", G5>0),VLOOKUP(H5,$A$52:$B$63,2,FALSE)-G5+VLOOKUP(H5,$A$25:$B$36,2,FALSE),"") | K5: 2.7KG FIESTA | L5: ='DAILY STOCKS (F)'!U5 -> 6 | M5: 0 | N5: 0 | O5: =C15 -> 0 | P5: =C27 -> 1 | Q5: =COUNTIF($H$3:$H$25,K5) -> 0 | R5: =C39 -> 0 | T5: =L5+M5+N5-O5-P5-Q5-R5-S5 -> 5 | U5: 5 | V5: =U5-T5 -> 0 | X5: 207803 | Y5: CARAG | Z5: 1 NGT | AA5: 963 | AB5: 50
A6: OTHERS | F6: NONE | H6: NONE | I6: =IF(AND(F6<>"NONE",H6<>"NONE", G6>0),VLOOKUP(H6,$A$52:$B$63,2,FALSE)-G6+VLOOKUP(H6,$A$25:$B$36,2,FALSE),"") | K6: 7KG PASAK | L6: ='DAILY STOCKS (F)'!U6 -> 9 | M6: 0 | N6: 0 | O6: =C16 -> 0 | P6: =C28 -> 1 | Q6: =COUNTIF($H$3:$H$25,K6) -> 0 | R6: =C40 -> 0 | T6: =L6+M6+N6-O6-P6-Q6-R6-S6 -> 8 | U6: 8 | V6: =U6-T6 -> 0 | X6: 207804 | Y6: SAMAR | Z6: 1 PV | AA6: 963 | AB6: 50
A7: GS-3 | B7: 650 | C7: 0 | D7: =C7*B7 -> 0 | F7: NONE | H7: NONE | I7: =IF(AND(F7<>"NONE",H7<>"NONE", G7>0),VLOOKUP(H7,$A$52:$B$63,2,FALSE)-G7+VLOOKUP(H7,$A$25:$B$36,2,FALSE),"") | K7: 7KG RUSKAS | L7: ='DAILY STOCKS (F)'!U7 -> 17 | M7: 0 | N7: 0 | O7: =C17 -> 0 | P7: =C29 -> 4 | Q7: =COUNTIF($H$3:$H$25,K7) -> 0 | R7: =C41 -> 0 | T7: =L7+M7+N7-O7-P7-Q7-R7-S7 -> 13 | U7: 13 | V7: =U7-T7 -> 0 | X7: 207805 | Y7: AMPONGAN | Z7: 1 NGT | AA7: 988 | AB7: 25
A8: HOSE | B8: 180 | C8: 0 | D8: =C8*B8 -> 0 | F8: NONE | H8: NONE | I8: =IF(AND(F8<>"NONE",H8<>"NONE", G8>0),VLOOKUP(H8,$A$52:$B$63,2,FALSE)-G8+VLOOKUP(H8,$A$25:$B$36,2,FALSE),"") | K8: 11KG PASAK | L8: ='DAILY STOCKS (F)'!U8 -> 19 | M8: 0 | N8: 67 | O8: =C18 -> 0 | P8: =C30 -> 67 | Q8: =COUNTIF($H$3:$H$25,K8) -> 0 | R8: =C42 -> 0 | S8: 14 | T8: =L8+M8+N8-O8-P8-Q8-R8-S8 -> 5 | U8: 5 | V8: =U8-T8 -> 0 | X8: 207806 | Y8: CAPISTRANO | Z8: 1 PV | AA8: 963 | AB8: 50
A9: CLAMP | B9: 20 | C9: 0 | D9: =C9*B9 -> 0 | F9: NONE | H9: NONE | I9: =IF(AND(F9<>"NONE",H9<>"NONE", G9>0),VLOOKUP(H9,$A$52:$B$63,2,FALSE)-G9+VLOOKUP(H9,$A$25:$B$36,2,FALSE),"") | K9: 11KG RUSKAS | L9: ='DAILY STOCKS (F)'!U9 -> 23 | M9: O | N9: 50 | O9: =C19 -> 0 | P9: =C31 -> 55 | Q9: =COUNTIF($H$3:$H$25,K9) -> 0 | R9: =C43 -> 0 | S9: 5 | T9: =L9+M9+N9-O9-P9-Q9-R9-S9 -> #VALUE! | U9: 13 | V9: =U9-T9 -> #VALUE! | X9: 207807 | Y9: SAN ISIDRO | Z9: 1 NGT | AC9: 1013
A10: REYNA (SINGLE BURNER) | B10: 650 | C10: 0 | D10: =C10*B10 -> 0 | F10: NONE | H10: NONE | I10: =IF(AND(F10<>"NONE",H10<>"NONE", G10>0),VLOOKUP(H10,$A$52:$B$63,2,FALSE)-G10+VLOOKUP(H10,$A$25:$B$36,2,FALSE),"") | K10: ELITE PASAK | L10: ='DAILY STOCKS (F)'!U10 -> 8 | M10: 0 | N10: 0 | O10: =C20 -> 0 | P10: =C32 -> 0 | Q10: =COUNTIF($H$3:$H$25,K10) -> 0 | R10: =C44 -> 0 | T10: =L10+M10+N10-O10-P10-Q10-R10-S10 -> 8 | U10: 8 | V10: =U10-T10 -> 0 | Z10: 3 PV | AC10: 3039
A11: REYNA (DOUBLE BURNER) | B11: 1200 | C11: 0 | D11: =C11*B11 -> 0 | F11: NONE | H11: NONE | I11: =IF(AND(F11<>"NONE",H11<>"NONE", G11>0),VLOOKUP(H11,$A$52:$B$63,2,FALSE)-G11+VLOOKUP(H11,$A$25:$B$36,2,FALSE),"") | K11: ELITE RUSKAS | L11: ='DAILY STOCKS (F)'!U11 -> 11 | M11: 0 | N11: 0 | O11: =C21 -> 0 | P11: =C33 -> 0 | Q11: =COUNTIF($H$3:$H$25,K11) -> 0 | R11: =C45 -> 0 | T11: =L11+M11+N11-O11-P11-Q11-R11-S11 -> 11 | U11: 11 | V11: =U11-T11 -> 0 | X11: 207808 | Y11: CADLAN | Z11: 3 2.7KG | AC11: 840
A12: Y TYPE | B12: 150 | C12: 0 | D12: =C12*B12 -> 0 | F12: NONE | H12: NONE | I12: =IF(AND(F12<>"NONE",H12<>"NONE", G12>0),VLOOKUP(H12,$A$52:$B$63,2,FALSE)-G12+VLOOKUP(H12,$A$25:$B$36,2,FALSE),"") | K12: 22KG | L12: ='DAILY STOCKS (F)'!U12 -> 3 | M12: 0 | N12: 0 | O12: =C22 -> 0 | P12: =C34 -> 2 | Q12: =COUNTIF($H$3:$H$25,K12) -> 0 | R12: =C46 -> 0 | T12: =L12+M12+N12-O12-P12-Q12-R12-S12 -> 1 | U12: 1 | V12: =U12-T12 -> 0 | Z12: 6 NGT | AC12: 6078
A13: CYLINDER WITH REFILL | F13: NONE | H13: NONE | I13: =IF(AND(F13<>"NONE",H13<>"NONE", G13>0),VLOOKUP(H13,$A$52:$B$63,2,FALSE)-G13+VLOOKUP(H13,$A$25:$B$36,2,FALSE),"") | K13: 50KG BLUE | L13: ='DAILY STOCKS (F)'!U13 | M13: 0 | N13: 0 | O13: =C23 -> 0 | P13: =C35 -> 0 | Q13: =COUNTIF($H$3:$H$25,K13) -> 0 | R13: =C47 -> 0 | T13: =L13+M13+N13-O13-P13-Q13-R13-S13 -> 0 | V13: =U13-T13 -> 0 | Z13: 8 PV | AC13: 8104
A14: 2.7KG | B14: =B26+B53 -> 1480 | C14: 0 | D14: =C14*B14 -> 0 | F14: NONE | H14: NONE | I14: =IF(AND(F14<>"NONE",H14<>"NONE", G14>0),VLOOKUP(H14,$A$52:$B$63,2,FALSE)-G14+VLOOKUP(H14,$A$25:$B$36,2,FALSE),"") | K14: 50KG CODED | L14: ='DAILY STOCKS (F)'!U14 -> 4 | M14: 0 | N14: 0 | O14: =C24 -> 0 | P14: =C36 -> 1 | Q14: =COUNTIF($H$3:$H$25,K14) -> 0 | R14: =C48 -> 0 | T14: =L14+M14+N14-O14-P14-Q14-R14-S14 -> 3 | U14: 3 | V14: =U14-T14 -> 0 | X14: 207809 | Y14: BONA | Z14: 1 NGT | AA14: 988 | AB14: 25
A15: 2.7KG FIESTA | B15: =B27+B54 -> 1480 | C15: 0 | D15: =C15*B15 -> 0 | F15: NONE | H15: NONE | I15: =IF(AND(F15<>"NONE",H15<>"NONE", G15>0),VLOOKUP(H15,$A$52:$B$63,2,FALSE)-G15+VLOOKUP(H15,$A$25:$B$36,2,FALSE),"") | X15: 207810 | Y15: DASMARINAS | Z15: 1 NGT | AA15: 963 | AB15: 50
A16: 7KG PASAK | B16: =B28+B55 -> 2588 | C16: 0 | D16: =C16*B16 -> 0 | F16: NONE | H16: NONE | I16: =IF(AND(F16<>"NONE",H16<>"NONE", G16>0),VLOOKUP(H16,$A$52:$B$63,2,FALSE)-G16+VLOOKUP(H16,$A$25:$B$36,2,FALSE),"") | X16: 207811 | Y16: STA ANA | Z16: 1 7PV | AA16: 688
A17: 7KG RUSKAS | B17: =B29+B56 -> 2588 | C17: 0 | D17: =C17*B17 -> 0 | F17: NONE | H17: NONE | I17: =IF(AND(F17<>"NONE",H17<>"NONE", G17>0),VLOOKUP(H17,$A$52:$B$63,2,FALSE)-G17+VLOOKUP(H17,$A$25:$B$36,2,FALSE),"") | K17: EMPTY | L17: BEG | M17: PLANTA | N17: REFILL | O17: SWAP | P17: RETURNED | Q17: END | R17: AUD | S17: VAR | X17: 207812 | Y17: DELOS REYES | Z17: 1 2.7KG F | AA17: 280
A18: 11KG PASAK | B18: =B30+B57 -> 3013 | C18: 0 | D18: =C18*B18 -> 0 | F18: NONE | H18: NONE | I18: =IF(AND(F18<>"NONE",H18<>"NONE", G18>0),VLOOKUP(H18,$A$52:$B$63,2,FALSE)-G18+VLOOKUP(H18,$A$25:$B$36,2,FALSE),"") | K18: 2.7KG | L18: ='DAILY STOCKS (F)'!R18 -> 41 | M18: =N4 -> 0 | N18: =P4 -> 9 | O18: =countif($F$3:$F$25,K18) -> 0 | Q18: =L18-M18+N18+O18+P18 -> 50 | R18: 50 | S18: =R18-Q18 -> 0 | X18: 207813 | Y18: BONITA | Z18: 16 PV | AA18: 15008 | AB18: 1200
A19: 11KG RUSKAS | B19: =B31+B58 -> 3013 | C19: 0 | D19: =C19*B19 -> 0 | F19: NONE | H19: NONE | I19: =IF(AND(F19<>"NONE",H19<>"NONE", G19>0),VLOOKUP(H19,$A$52:$B$63,2,FALSE)-G19+VLOOKUP(H19,$A$25:$B$36,2,FALSE),"") | K19: 2.7KG FIESTA | L19: ='DAILY STOCKS (F)'!R19 -> 11 | M19: =N5 -> 0 | N19: =P5 -> 1 | O19: =countif($F$3:$F$25,K19) -> 0 | Q19: =L19-M19+N19+O19+P19 -> 12 | R19: 12 | S19: =R19-Q19 -> 0 | Z19: 27 NGT | AA19: 25326 | AB19: 2025
A20: ELITE PASAK | B20: =B32+B59 -> 4738 | C20: 0 | D20: =C20*B20 -> 0 | F20: NONE | H20: NONE | I20: =IF(AND(F20<>"NONE",H20<>"NONE", G20>0),VLOOKUP(H20,$A$52:$B$63,2,FALSE)-G20+VLOOKUP(H20,$A$25:$B$36,2,FALSE),"") | K20: 7KG PASAK | L20: ='DAILY STOCKS (F)'!R20 -> 10 | M20: =N6 -> 0 | N20: =P6 -> 1 | O20: =countif($F$3:$F$25,K20) -> 0 | Q20: =L20-M20+N20+O20+P20 -> 11 | R20: 11 | S20: =R20-Q20 -> 0 | X20: 207814 | Y20: MIEKOY | Z20: 1 50CODED | AA20: 4059 | AB20: 400
A21: ELITE RUSKAS | B21: =B33+B60 -> 4738 | C21: 0 | D21: =C21*B21 -> 0 | F21: NONE | H21: NONE | I21: =IF(AND(F21<>"NONE",H21<>"NONE", G21>0),VLOOKUP(H21,$A$52:$B$63,2,FALSE)-G21+VLOOKUP(H21,$A$25:$B$36,2,FALSE),"") | K21: 7KG RUSKAS | L21: ='DAILY STOCKS (F)'!R21 -> 14 | M21: =N7 -> 0 | N21: =P7 -> 4 | O21: =countif($F$3:$F$25,K21) -> 0 | Q21: =L21-M21+N21+O21+P21 -> 18 | R21: 18 | S21: =R21-Q21 -> 0 | X21: 207815 | Y21: BERMUDO | Z21: 1 PV | AA21: 963 | AB21: 50
A22: 22KG | B22: =B34+B61 -> 5665 | C22: 0 | D22: =C22*B22 -> 0 | F22: NONE | H22: NONE | I22: =IF(AND(F22<>"NONE",H22<>"NONE", G22>0),VLOOKUP(H22,$A$52:$B$63,2,FALSE)-G22+VLOOKUP(H22,$A$25:$B$36,2,FALSE),"") | K22: 11KG PASAK | L22: ='DAILY STOCKS (F)'!R22 -> 146 | M22: =N8 -> 67 | N22: =P8 -> 67 | O22: =countif($F$3:$F$25,K22) -> 0 | Q22: =L22-M22+N22+O22+P22 -> 146 | R22: 146 | S22: =R22-Q22 -> 0 | X22: 207817 | Y22: BUENAFE | Z22: 1 2.7KG | AA22: 280
A23: 50KG BLUE | B23: =B35+B62 -> 9459 | C23: 0 | D23: =C23*B23 -> 0 | F23: NONE | H23: NONE | I23: =IF(AND(F23<>"NONE",H23<>"NONE", G23>0),VLOOKUP(H23,$A$52:$B$63,2,FALSE)-G23+VLOOKUP(H23,$A$25:$B$36,2,FALSE),"") | K23: 11KG RUSKAS | L23: ='DAILY STOCKS (F)'!R23 -> 117 | M23: =N9 -> 50 | N23: =C31 -> 55 | O23: =countif($F$3:$F$25,K23) -> 0 | Q23: =L23-M23+N23+O23+P23 -> 122 | R23: 136 | S23: =R23-Q23 -> 14 | X23: 207818 | Y23: TIGAON | Z23: 12 NGT | AA23: 11256 | AB23: 900
A24: 50KG CODED | B24: =B36+B63 -> 9459 | C24: 0 | D24: =C24*B24 -> 0 | F24: NONE | H24: NONE | I24: =IF(AND(F24<>"NONE",H24<>"NONE", G24>0),VLOOKUP(H24,$A$52:$B$63,2,FALSE)-G24+VLOOKUP(H24,$A$25:$B$36,2,FALSE),"") | K24: ELITE PASAK | L24: ='DAILY STOCKS (F)'!R24 -> 2 | M24: =N10 -> 0 | N24: =P10 -> 0 | O24: =countif($F$3:$F$25,K24) -> 0 | Q24: =L24-M24+N24+O24+P24 -> 2 | R24: 2 | S24: =R24-Q24 -> 0 | Z24: 5 PV | AA24: 4690 | AB24: 375
A25: REFILL | F25: NONE | H25: NONE | I25: =IF(AND(F25<>"NONE",H25<>"NONE", G25>0),VLOOKUP(H25,$A$52:$B$63,2,FALSE)-G25+VLOOKUP(H25,$A$25:$B$36,2,FALSE),"") | K25: ELITE RUSKAS | L25: ='DAILY STOCKS (F)'!R25 -> 64 | M25: =N11 -> 0 | N25: =P11 -> 0 | O25: =countif($F$3:$F$25,K25) -> 0 | Q25: =L25-M25+N25+O25+P25 -> 64 | R25: 64 | S25: =R25-Q25 -> 0 | X25: 207820 | Y25: BLANCADA | Z25: 2 NGT | AA25: 2026
A26: 2.7KG | B26: 280 | C26: 9 | D26: =C26*B26 -> 2520 | F26: TOTAL SALES | I26: =sum(I3:I25) -> 0 | K26: 22KG | L26: ='DAILY STOCKS (F)'!R26 -> 3 | M26: =N12 -> 0 | N26: =P12 -> 2 | O26: =countif($F$3:$F$25,K26) -> 0 | Q26: =L26-M26+N26+O26+P26 -> 5 | R26: 5 | S26: =R26-Q26 -> 0 | X26: 207821 | Y26: ORASCO | Z26: 1 NGT | AA26: 963 | AB26: 50
A27: 2.7KG FIESTA | B27: 280 | C27: 1 | D27: =C27*B27 -> 280 | K27: 50KG BLUE | L27: ='DAILY STOCKS (F)'!R27 -> 31 | M27: =N13 -> 0 | N27: =P13 -> 0 | O27: =countif($F$3:$F$25,K27) -> 0 | Q27: =L27-M27+N27+O27+P27 -> 31 | R27: 31 | S27: =R27-Q27 -> 0 | X27: 207822 | Y27: SAN ISIDRO | Z27: 2 PV | AC27: 2026
A28: 7KG PASAK | B28: 688 | C28: 1 | D28: =C28*B28 -> 688 | K28: 50KG CODED | L28: ='DAILY STOCKS (F)'!R28 -> 12 | M28: =N14 -> 0 | N28: =P14 -> 1 | O28: =countif($F$3:$F$25,K28) -> 0 | Q28: =L28-M28+N28+O28+P28 -> 13 | R28: 13 | S28: =R28-Q28 -> 0 | Z28: 1 NGT | AC28: 1013
A29: 7KG RUSKAS | B29: 688 | C29: 4 | D29: =C29*B29 -> 2752 | X29: 207823 | Y29: CADLAN | Z29: 5 PV | AC29: 5065
A30: 11KG PASAK | B30: 1013 | C30: 67 | D30: =C30*B30 -> 67871 | Z30: 5 NGT | AC30: 5065
A31: 11KG RUSKAS | B31: 1013 | C31: 55 | D31: =C31*B31 -> 55715 | K31: ACCESSORIES | L31: BEG | M31: DELIVERY | N31: SOLD | O31: DEFECTIVE | P31: END | Q31: AUD | R31: VAR | X31: 207824 | Y31: NALLATAN | Z31: 1 PV | AA31: 938 | AB31: 75
A32: ELITE PASAK | B32: 1038 | C32: 0 | D32: =C32*B32 -> 0 | K32: REGULATOR | X32: 207825 | Y32: YAMSON | Z32: 3 PV | AA32: 2814 | AB32: 225
A33: ELITE RUSKAS | B33: 1038 | C33: 0 | D33: =C33*B33 -> 0 | K33: REGULATOR (PASAK) | L33: ='DAILY STOCKS (F)'!Q33 | M33: 0 | N33: =C4 -> 0 | P33: =L33+M33-N33-O33 -> 0 | R33: =Q33-P33 -> 0 | X33: 207826 | Y33: SOLA | Z33: 1 NGT | AA33: 963 | AB33: 50
A34: 22KG | B34: 1965 | C34: 2 | D34: =C34*B34 -> 3930 | K34: REGULATOR (RUSKAS) | L34: ='DAILY STOCKS (F)'!Q34 -> 11 | M34: 0 | N34: =C5 -> 0 | P34: =L34+M34-N34-O34 -> 11 | Q34: 11 | R34: =Q34-P34 -> 0 | X34: 207827 | Y34: TADURAN | Z34: 1 NGT | AA34: 963 | AB34: 50
A35: 50KG BLUE | B35: 4459 | C35: 0 | D35: =C35*B35 -> 0 | K35: OTHERS | X35: 207828 | Y35: SAN ISIDRO | Z35: 2 PV | AC35: 2026
A36: 50KG CODED | B36: 4459 | C36: 1 | D36: =C36*B36 -> 4459 | K36: GS-3 | L36: ='DAILY STOCKS (F)'!Q36 -> 18 | M36: 0 | N36: =C7 -> 0 | P36: =L36+M36-N36-O36 -> 18 | Q36: 18 | R36: =Q36-P36 -> 0 | Z36: 1 NGT | AC36: 1013
A37: BORROW | K37: HOSE | L37: ='DAILY STOCKS (F)'!Q37 -> 2 | M37: 0 | N37: =C8 -> 0 | P37: =L37+M37-N37-O37 -> 2 | Q37: 2 | R37: =Q37-P37 -> 0 | X37: 207829 | Y37: MELLIZA | Z37: 1 2.7KG | AA37: 268 | AB37: 12
A38: 2.7KG | B38: =B26 -> 280 | C38: 0 | D38: =C38*B38 -> 0 | K38: CLAMP | L38: ='DAILY STOCKS (F)'!Q38 -> 84 | M38: 0 | N38: =C9 -> 0 | P38: =L38+M38-N38-O38 -> 84 | Q38: 84 | R38: =Q38-P38 -> 0 | X38: 207830 | Y38: VALIENTE | Z38: 1 PV | AA38: 938 | AB38: 75
A39: 2.7KG FIESTA | B39: =B27 -> 280 | C39: 0 | D39: =C39*B39 -> 0 | K39: REYNA (SINGLE BURNER) | L39: ='DAILY STOCKS (F)'!Q39 | M39: 0 | N39: =C10 -> 0 | P39: =L39+M39-N39-O39 -> 0 | R39: =Q39-P39 -> 0 | X39: 207831 | Y39: NACARIO | Z39: 2 PV | AA39: 1876 | AB39: 150
A40: 7KG PASAK | B40: =B28 -> 688 | C40: 0 | D40: =C40*B40 -> 0 | K40: REYNA (DOUBLE BURNER) | L40: ='DAILY STOCKS (F)'!Q40 | M40: 0 | N40: =C11 -> 0 | P40: =L40+M40-N40-O40 -> 0 | R40: =Q40-P40 -> 0 | X40: 207832 | Y40: SAN ISIDRO | Z40: 1 7NGT | AC40: 688
A41: 7KG RUSKAS | B41: =B29 -> 688 | C41: 0 | D41: =C41*B41 -> 0 | K41: Y TYPE | L41: ='DAILY STOCKS (F)'!Q41 | M41: 0 | N41: =C12 -> 0 | P41: =L41+M41-N41-O41 -> 0 | R41: =Q41-P41 -> 0 | X41: 207833 | Y41: VILLAR | Z41: 1 NGT | AA41: 963 | AB41: 50
A42: 11KG PASAK | B42: =B30 -> 1013 | C42: 0 | D42: =C42*B42 -> 0 | X42: 207834 | Y42: HERNANDEZ | Z42: 1 PV | AA42: 938 | AB42: 75
A43: 11KG RUSKAS | B43: =B31 -> 1013 | C43: 0 | D43: =C43*B43 -> 0 | X43: 207835 | Y43: AURILLO | Z43: 1 22KG | AA43: 1789 | AB43: 176
A44: ELITE PASAK | B44: =B32 -> 1038 | C44: 0 | D44: =C44*B44 -> 0 | K44: TOTAL CYLINDER | L44: BEG | M44: END | N44: VAR | O44: COMMENTS | X44: 207836 | Y44: ABOVE | Z44: 1 PV | AA44: 938 | AB44: 75
A45: ELITE RUSKAS | B45: =B33 -> 1038 | C45: 0 | D45: =C45*B45 -> 0 | K45: 2.7KG | L45: =L4+L18 -> 68 | M45: =T4+Q18 -> 68 | N45: =M45-L45 -> 0 | X45: 207837 | Y45: MALICAD | Z45: 1 PV | AA45: 963 | AB45: 50
A46: 22KG | B46: =B34 -> 1965 | C46: 0 | D46: =C46*B46 -> 0 | K46: 2.7KG FIESTA | L46: =L5+L19 -> 17 | M46: =T5+Q19 -> 17 | N46: =M46-L46 -> 0 | X46: 207838 | Y46: PABLO | Z46: 1 2.7KG | AA46: 280
A47: 50KG BLUE | B47: =B35 -> 4459 | C47: 0 | D47: =C47*B47 -> 0 | K47: 7KG (PASAK) | L47: =L6+L20 -> 19 | M47: =T6+Q20 -> 19 | N47: =M47-L47 -> 0 | X47: 207839 | Y47: GCCU | Z47: 1 7PV | AA47: 667 | AB47: 21
A48: 50KG CODED | B48: =B36 -> 4459 | C48: 0 | D48: =C48*B48 -> 0 | K48: 7KG (RUSKAS) | L48: =L7+L21 -> 31 | M48: =T7+Q21 -> 31 | N48: =M48-L48 -> 0 | X48: 207840 | Y48: BATO | Z48: 1 2.7KG | AA48: 280
A49: TOTAL SALES | D49: =sum(D4:D48) -> 138215 | K49: 11KG (PASAK) | L49: =L8+L22 -> 165 | M49: =T8+Q22 -> 151 | N49: =M49-L49 -> -14 | O49: NEGATIVE, BINALIK SA STORE | X49: 207841 | Y49: NIERVA | Z49: 1 PV | AA49: 938 | AB49: 75
K50: 11KG (RUSKAS) | L50: =L9+L23 -> 140 | M50: =T9+Q23 -> #VALUE! | N50: =M50-L50 -> #VALUE! | X50: 207842 | Y50: SAN ISIDRO | Z50: 3 NGT | AC50: 3039
K51: ELITE (PASAK) | L51: =L10+L24 -> 10 | M51: =T10+Q24 -> 10 | N51: =M51-L51 -> 0 | X51: 207843 | Y51: VALIENTE | Z51: 1 NGT | AA51: 938 | AB51: 75
A52: CYLINDER PRICE LIST | B52: PRICE | K52: ELITE (RUSKAS) | L52: =L11+L25 -> 75 | M52: =T11+Q25 -> 75 | N52: =M52-L52 -> 0 | X52: 207844 | Y52: ARINO | Z52: 1 2.7KG | AA52: 280
A53: 2.7KG | B53: 1200 | K53: 22KG | L53: =L12+L26 -> 6 | M53: =T12+Q26 -> 6 | N53: =M53-L53 -> 0 | X53: 207845 | Y53: FLORA | Z53: 1 7PV | AA53: 688
A54: 2.7KG FIESTA | B54: 1200 | K54: 50KG (BLUE) | L54: =L13+L27 -> 31 | M54: =T13+Q27 -> 31 | N54: =M54-L54 -> 0 | X54: 207846 | Y54: MERANO | Z54: 1 7PV | AA54: 688
A55: 7KG PASAK | B55: 1900 | K55: 50KG (CODED) | L55: =L14+L28 -> 16 | M55: =T14+Q28 -> 16 | N55: =M55-L55 -> 0
A56: 7KG RUSKAS | B56: 1900
A57: 11KG PASAK | B57: 2000
A58: 11KG RUSKAS | B58: 2000 | K58: BORROWED | L58: BEG | M58: BORROWED | N58: RETURNED | O58: END
A59: ELITE PASAK | B59: 3700 | K59: 2.7KG | L59: ='DAILY STOCKS (F)'!O59 -> 0 | M59: =R4 -> 0 | N59: =P18 | O59: =L59+M59-N59 -> 0
A60: ELITE RUSKAS | B60: 3700 | K60: 2.7KG FIESTA | L60: ='DAILY STOCKS (F)'!O60 -> 0 | M60: =R5 -> 0 | N60: =P19 | O60: =L60+M60-N60 -> 0
A61: 22KG | B61: 3700 | K61: 7KG (PASAK) | L61: ='DAILY STOCKS (F)'!O61 -> 0 | M61: =R6 -> 0 | N61: =P20 | O61: =L61+M61-N61 -> 0
A62: 50KG BLUE | B62: 5000 | K62: 7KG (RUSKAS) | L62: ='DAILY STOCKS (F)'!O62 -> 0 | M62: =R7 -> 0 | N62: =P21 | O62: =L62+M62-N62 -> 0
A63: 50KG CODED | B63: 5000 | K63: 11KG (PASAK) | L63: ='DAILY STOCKS (F)'!O63 -> -1 | M63: =R8 -> 0 | N63: =P22 | O63: =L63+M63-N63 -> -1
K64: 11KG (RUSKAS) | L64: ='DAILY STOCKS (F)'!O64 -> 0 | M64: =R9 -> 0 | N64: =P23 | O64: =L64+M64-N64 -> 0
K65: ELITE (PASAK) | L65: ='DAILY STOCKS (F)'!O65 -> 0 | M65: =R10 -> 0 | N65: =P24 | O65: =L65+M65-N65 -> 0
K66: ELITE (RUSKAS) | L66: ='DAILY STOCKS (F)'!O66 -> 0 | M66: =R11 -> 0 | N66: =P25 | O66: =L66+M66-N66 -> 0
K67: 22KG | L67: ='DAILY STOCKS (F)'!O67 -> 0 | M67: =R12 -> 0 | N67: =P26 | O67: =L67+M67-N67 -> 0
K68: 50KG (BLUE) | L68: ='DAILY STOCKS (F)'!O68 -> 0 | M68: =R13 -> 0 | N68: =P27 | O68: =L68+M68-N68 -> 0
K69: 50KG (CODED) | L69: ='DAILY STOCKS (F)'!O69 -> 0 | M69: =R14 -> 0 | N69: =P28 | O69: =L69+M69-N69 -> 0
X105: TOTAL | AA105: =SUM(AA3:AA104) -> 92546 | AB105: =SUM(AB3:AB104) -> 6660 | AC105: =SUM(AC3:AC104) -> 39009 | AD105: =SUM(AD3:AD104) -> 0

Sheet DAILY STOCKS (SUN)
F1: UPGRADE / SWAP | K1: DAILYSTOCKS MONITORING | X1: DISCOUNTS
A2: PRODUCT NAME | B2: SRP | C2: SOLD | D2: TOTAL SALES | F2: PRODUCT TO SWAP | G2: PURCHASE PRICE | H2: PRODUCT TO BUY | I2: TOTAL SALES | K2: STOCKS | L2: BEG | M2: PLANTA PURCHASES | N2: PLANTA REFILL | O2: SOLD | P2: REFILL | Q2: SWAP | R2: BORROWED | S2: RETURN | T2: END | U2: AUD | V2: VAR | X2: INVOICE | Y2: NAME | Z2: PARTICULARS | AA2: CASH | AB2: DISCOUNT | AC2: A/R | AD2: AMOUNT
A3: REGULATOR | F3: NONE | H3: NONE | I3: =IF(AND(F3<>"NONE",H3<>"NONE", G3>0),VLOOKUP(H3,$A$52:$B$63,2,FALSE)-G3+VLOOKUP(H3,$A$25:$B$36,2,FALSE),"") | X3: 207847 | Y3: TIMOLA | Z3: 1 PV | AA3: 938 | AB3: 75
A4: REGULATOR (PASAK) | B4: 650 | C4: 0 | D4: =C4*B4 -> 0 | F4: NONE | H4: NONE | I4: =IF(AND(F4<>"NONE",H4<>"NONE", G4>0),VLOOKUP(H4,$A$52:$B$63,2,FALSE)-G4+VLOOKUP(H4,$A$25:$B$36,2,FALSE),"") | K4: 2.7KG | L4: ='DAILY STOCKS (SAT)'!U4 -> 18 | M4: 0 | N4: 0 | O4: =C14 -> 1 | P4: =C26 -> 9 | Q4: =COUNTIF($H$3:$H$25,K4) -> 0 | R4: =C38 -> 0 | T4: =L4+M4+N4-O4-P4-Q4-R4-S4 -> 8 | U4: 9 | V4: =U4-T4 -> 1 | Z4: 1 50KG CODED | AA4: 4059 | AB4: 400
A5: REGULATOR (RUSKAS) | B5: 375 | C5: 4 | D5: =C5*B5 -> 1500 | F5: NONE | H5: NONE | I5: =IF(AND(F5<>"NONE",H5<>"NONE", G5>0),VLOOKUP(H5,$A$52:$B$63,2,FALSE)-G5+VLOOKUP(H5,$A$25:$B$36,2,FALSE),"") | K5: 2.7KG FIESTA | L5: ='DAILY STOCKS (SAT)'!U5 -> 5 | M5: 0 | N5: 0 | O5: =C15 -> 0 | P5: =C27 -> 0 | Q5: =COUNTIF($H$3:$H$25,K5) -> 0 | R5: =C39 -> 0 | T5: =L5+M5+N5-O5-P5-Q5-R5-S5 -> 5 | U5: 4 | V5: =U5-T5 -> -1 | X5: 207848 | Y5: FIGURA | Z5: 1 2.7KG | AA5: 280
A6: OTHERS | F6: NONE | H6: NONE | I6: =IF(AND(F6<>"NONE",H6<>"NONE", G6>0),VLOOKUP(H6,$A$52:$B$63,2,FALSE)-G6+VLOOKUP(H6,$A$25:$B$36,2,FALSE),"") | K6: 7KG PASAK | L6: ='DAILY STOCKS (SAT)'!U6 -> 8 | M6: 0 | N6: 0 | O6: =C16 -> 0 | P6: =C28 -> 0 | Q6: =COUNTIF($H$3:$H$25,K6) -> 0 | R6: =C40 -> 0 | T6: =L6+M6+N6-O6-P6-Q6-R6-S6 -> 8 | U6: 8 | V6: =U6-T6 -> 0 | X6: 207849 | Y6: BENITEZ | Z6: 1 PV | AA6: 963 | AB6: 50
A7: GS-3 | B7: 650 | C7: 1 | D7: =C7*B7 -> 650 | F7: NONE | H7: NONE | I7: =IF(AND(F7<>"NONE",H7<>"NONE", G7>0),VLOOKUP(H7,$A$52:$B$63,2,FALSE)-G7+VLOOKUP(H7,$A$25:$B$36,2,FALSE),"") | K7: 7KG RUSKAS | L7: ='DAILY STOCKS (SAT)'!U7 -> 13 | M7: 0 | N7: 0 | O7: =C17 -> 0 | P7: =C29 -> 0 | Q7: =COUNTIF($H$3:$H$25,K7) -> 0 | R7: =C41 -> 0 | T7: =L7+M7+N7-O7-P7-Q7-R7-S7 -> 13 | U7: 13 | V7: =U7-T7 -> 0 | X7: 207850 | Y7: BULALACAO | Z7: 1 PV | AA7: 963 | AB7: 50
A8: HOSE | B8: 180 | C8: 2 | D8: =C8*B8 -> 360 | F8: NONE | H8: NONE | I8: =IF(AND(F8<>"NONE",H8<>"NONE", G8>0),VLOOKUP(H8,$A$52:$B$63,2,FALSE)-G8+VLOOKUP(H8,$A$25:$B$36,2,FALSE),"") | K8: 11KG PASAK | L8: ='DAILY STOCKS (SAT)'!U8 -> 5 | M8: 0 | N8: 70 | O8: =C18 -> 0 | P8: =C30 -> 42 | Q8: =COUNTIF($H$3:$H$25,K8) -> 0 | R8: =C42 -> 0 | T8: =L8+M8+N8-O8-P8-Q8-R8-S8 -> 33 | U8: 33 | V8: =U8-T8 -> 0 | X8: 209556 | Y8: NAS | Z8: 1 NGT | AA8: 988 | AB8: 25
A9: CLAMP | B9: 20 | C9: 3 | D9: =C9*B9 -> 60 | F9: NONE | H9: NONE | I9: =IF(AND(F9<>"NONE",H9<>"NONE", G9>0),VLOOKUP(H9,$A$52:$B$63,2,FALSE)-G9+VLOOKUP(H9,$A$25:$B$36,2,FALSE),"") | K9: 11KG RUSKAS | L9: ='DAILY STOCKS (SAT)'!U9 -> 13 | M9: 0 | N9: 70 | O9: =C19 -> 2 | P9: =C31 -> 48 | Q9: =COUNTIF($H$3:$H$25,K9) -> 0 | R9: =C43 -> 0 | T9: =L9+M9+N9-O9-P9-Q9-R9-S9 -> 33 | U9: 33 | V9: =U9-T9 -> 0 | X9: 209557 | Y9: BILANDO | Z9: 1 NGT | AA9: 988 | AB9: 25
A10: REYNA (SINGLE BURNER) | B10: 650 | C10: 0 | D10: =C10*B10 -> 0 | F10: NONE | H10: NONE | I10: =IF(AND(F10<>"NONE",H10<>"NONE", G10>0),VLOOKUP(H10,$A$52:$B$63,2,FALSE)-G10+VLOOKUP(H10,$A$25:$B$36,2,FALSE),"") | K10: ELITE PASAK | L10: ='DAILY STOCKS (SAT)'!U10 -> 8 | M10: 0 | N10: 0 | O10: =C20 -> 0 | P10: =C32 -> 3 | Q10: =COUNTIF($H$3:$H$25,K10) -> 0 | R10: =C44 -> 0 | T10: =L10+M10+N10-O10-P10-Q10-R10-S10 -> 5 | U10: 5 | V10: =U10-T10 -> 0 | X10: 209558 | Y10: BONIFACIO | Z10: 1 NGT | AA10: 963 | AB10: 50
A11: REYNA (DOUBLE BURNER) | B11: 1200 | C11: 0 | D11: =C11*B11 -> 0 | F11: NONE | H11: NONE | I11: =IF(AND(F11<>"NONE",H11<>"NONE", G11>0),VLOOKUP(H11,$A$52:$B$63,2,FALSE)-G11+VLOOKUP(H11,$A$25:$B$36,2,FALSE),"") | K11: ELITE RUSKAS | L11: ='DAILY STOCKS (SAT)'!U11 -> 11 | M11: 0 | N11: 0 | O11: =C21 -> 0 | P11: =C33 -> 0 | Q11: =COUNTIF($H$3:$H$25,K11) -> 0 | R11: =C45 -> 0 | T11: =L11+M11+N11-O11-P11-Q11-R11-S11 -> 11 | U11: 11 | V11: =U11-T11 -> 0 | X11: 209559 | Y11: MANUGAD | Z11: 1 PV | AA11: 988 | AB11: 25
A12: Y TYPE | B12: 150 | C12: 0 | D12: =C12*B12 -> 0 | F12: NONE | H12: NONE | I12: =IF(AND(F12<>"NONE",H12<>"NONE", G12>0),VLOOKUP(H12,$A$52:$B$63,2,FALSE)-G12+VLOOKUP(H12,$A$25:$B$36,2,FALSE),"") | K12: 22KG | L12: ='DAILY STOCKS (SAT)'!U12 -> 1 | M12: 0 | N12: 0 | O12: =C22 -> 0 | P12: =C34 -> 0 | Q12: =COUNTIF($H$3:$H$25,K12) -> 0 | R12: =C46 -> 0 | T12: =L12+M12+N12-O12-P12-Q12-R12-S12 -> 1 | U12: 1 | V12: =U12-T12 -> 0 | X12: 209560 | Y12: BRAZAL | Z12: 1 2.7KG | AA12: 280
A13: CYLINDER WITH REFILL | F13: NONE | H13: NONE | I13: =IF(AND(F13<>"NONE",H13<>"NONE", G13>0),VLOOKUP(H13,$A$52:$B$63,2,FALSE)-G13+VLOOKUP(H13,$A$25:$B$36,2,FALSE),"") | K13: 50KG BLUE | L13: ='DAILY STOCKS (SAT)'!U13 | M13: 0 | N13: 3 | O13: =C23 -> 0 | P13: =C35 -> 2 | Q13: =COUNTIF($H$3:$H$25,K13) -> 0 | R13: =C47 -> 0 | T13: =L13+M13+N13-O13-P13-Q13-R13-S13 -> 1 | U13: 1 | V13: =U13-T13 -> 0 | X13: 209561 | Y13: FRIAS | Z13: 1 NGT | AA13: 988 | AB13: 25
A14: 2.7KG | B14: =B26+B53 -> 1480 | C14: 1 | D14: =C14*B14 -> 1480 | F14: NONE | H14: NONE | I14: =IF(AND(F14<>"NONE",H14<>"NONE", G14>0),VLOOKUP(H14,$A$52:$B$63,2,FALSE)-G14+VLOOKUP(H14,$A$25:$B$36,2,FALSE),"") | K14: 50KG CODED | L14: ='DAILY STOCKS (SAT)'!U14 -> 3 | M14: 0 | N14: 7 | O14: =C24 -> 0 | P14: =C36 -> 9 | Q14: =COUNTIF($H$3:$H$25,K14) -> 0 | R14: =C48 -> 0 | T14: =L14+M14+N14-O14-P14-Q14-R14-S14 -> 1 | U14: 1 | V14: =U14-T14 -> 0 | X14: 209562 | Y14: FRIAS | Z14: 1 NGT | AA14: 988 | AB14: 25
A15: 2.7KG FIESTA | B15: =B27+B54 -> 1480 | C15: 0 | D15: =C15*B15 -> 0 | F15: NONE | H15: NONE | I15: =IF(AND(F15<>"NONE",H15<>"NONE", G15>0),VLOOKUP(H15,$A$52:$B$63,2,FALSE)-G15+VLOOKUP(H15,$A$25:$B$36,2,FALSE),"") | X15: 209563 | Y15: IBBARIENTOS | Z15: 1 PV | AA15: 988 | AB15: 25
A16: 7KG PASAK | B16: =B28+B55 -> 2588 | C16: 0 | D16: =C16*B16 -> 0 | F16: NONE | H16: NONE | I16: =IF(AND(F16<>"NONE",H16<>"NONE", G16>0),VLOOKUP(H16,$A$52:$B$63,2,FALSE)-G16+VLOOKUP(H16,$A$25:$B$36,2,FALSE),"") | X16: 209564 | Y16: PRESENTATION | Z16: 1 PV | AA16: 988 | AB16: 25
A17: 7KG RUSKAS | B17: =B29+B56 -> 2588 | C17: 0 | D17: =C17*B17 -> 0 | F17: NONE | H17: NONE | I17: =IF(AND(F17<>"NONE",H17<>"NONE", G17>0),VLOOKUP(H17,$A$52:$B$63,2,FALSE)-G17+VLOOKUP(H17,$A$25:$B$36,2,FALSE),"") | K17: EMPTY | L17: BEG | M17: PLANTA | N17: REFILL | O17: SWAP | P17: RETURNED | Q17: END | R17: AUD | S17: VAR | X17: 209565 | Y17: BOMBASI | Z17: 1 PV | AA17: 988 | AB17: 25
A18: 11KG PASAK | B18: =B30+B57 -> 3013 | C18: 0 | D18: =C18*B18 -> 0 | F18: NONE | H18: NONE | I18: =IF(AND(F18<>"NONE",H18<>"NONE", G18>0),VLOOKUP(H18,$A$52:$B$63,2,FALSE)-G18+VLOOKUP(H18,$A$25:$B$36,2,FALSE),"") | K18: 2.7KG | L18: ='DAILY STOCKS (SAT)'!R18 -> 50 | M18: =N4 -> 0 | N18: =P4 -> 9 | O18: =countif($F$3:$F$25,K18) -> 0 | Q18: =L18-M18+N18+O18+P18 -> 59 | R18: 59 | S18: =R18-Q18 -> 0 | X18: 209566 | Y18: BRAGA | Z18: 1 PV | AA18: 963 | AB18: 50
A19: 11KG RUSKAS | B19: =B31+B58 -> 3013 | C19: 2 | D19: =C19*B19 -> 6026 | F19: NONE | H19: NONE | I19: =IF(AND(F19<>"NONE",H19<>"NONE", G19>0),VLOOKUP(H19,$A$52:$B$63,2,FALSE)-G19+VLOOKUP(H19,$A$25:$B$36,2,FALSE),"") | K19: 2.7KG FIESTA | L19: ='DAILY STOCKS (SAT)'!R19 -> 12 | M19: =N5 -> 0 | N19: =P5 -> 0 | O19: =countif($F$3:$F$25,K19) -> 0 | Q19: =L19-M19+N19+O19+P19 -> 12 | R19: 12 | S19: =R19-Q19 -> 0 | X19: 209567 | Y19: SAMAR | Z19: 1 NGT | AA19: 988 | AB19: 25
A20: ELITE PASAK | B20: =B32+B59 -> 4738 | C20: 0 | D20: =C20*B20 -> 0 | F20: NONE | H20: NONE | I20: =IF(AND(F20<>"NONE",H20<>"NONE", G20>0),VLOOKUP(H20,$A$52:$B$63,2,FALSE)-G20+VLOOKUP(H20,$A$25:$B$36,2,FALSE),"") | K20: 7KG PASAK | L20: ='DAILY STOCKS (SAT)'!R20 -> 11 | M20: =N6 -> 0 | N20: =P6 -> 0 | O20: =countif($F$3:$F$25,K20) -> 0 | Q20: =L20-M20+N20+O20+P20 -> 11 | R20: 11 | S20: =R20-Q20 -> 0 | X20: 209568 | Y20: RONO | Z20: 2 PV | AA20: 1876 | AB20: 150
A21: ELITE RUSKAS | B21: =B33+B60 -> 4738 | C21: 0 | D21: =C21*B21 -> 0 | F21: NONE | H21: NONE | I21: =IF(AND(F21<>"NONE",H21<>"NONE", G21>0),VLOOKUP(H21,$A$52:$B$63,2,FALSE)-G21+VLOOKUP(H21,$A$25:$B$36,2,FALSE),"") | K21: 7KG RUSKAS | L21: ='DAILY STOCKS (SAT)'!R21 -> 18 | M21: =N7 -> 0 | N21: =P7 -> 0 | O21: =countif($F$3:$F$25,K21) -> 0 | P21: 1 | Q21: =L21-M21+N21+O21+P21 -> 19 | R21: 18 | S21: =R21-Q21 -> -1 | X21: 209570 | Y21: NUNEZ | Z21: 1 PV CYLINDER | AA21: 2000
A22: 22KG | B22: =B34+B61 -> 5665 | C22: 0 | D22: =C22*B22 -> 0 | F22: NONE | H22: NONE | I22: =IF(AND(F22<>"NONE",H22<>"NONE", G22>0),VLOOKUP(H22,$A$52:$B$63,2,FALSE)-G22+VLOOKUP(H22,$A$25:$B$36,2,FALSE),"") | K22: 11KG PASAK | L22: ='DAILY STOCKS (SAT)'!R22 -> 146 | M22: =N8 -> 70 | N22: =P8 -> 42 | O22: =countif($F$3:$F$25,K22) -> 0 | Q22: =L22-M22+N22+O22+P22 -> 118 | R22: 154 | S22: =R22-Q22 -> 36 | Z22: 1 PV | AA22: 963 | AB22: 50
A23: 50KG BLUE | B23: =B35+B62 -> 9459 | C23: 0 | D23: =C23*B23 -> 0 | F23: NONE | H23: NONE | I23: =IF(AND(F23<>"NONE",H23<>"NONE", G23>0),VLOOKUP(H23,$A$52:$B$63,2,FALSE)-G23+VLOOKUP(H23,$A$25:$B$36,2,FALSE),"") | K23: 11KG RUSKAS | L23: ='DAILY STOCKS (SAT)'!R23 -> 136 | M23: =N9 -> 70 | N23: =C31 -> 48 | O23: =countif($F$3:$F$25,K23) -> 0 | Q23: =L23-M23+N23+O23+P23 -> 114 | R23: 111 | S23: =R23-Q23 -> -3 | Z23: 1 MREG | AA23: 325 | AB23: 50
A24: 50KG CODED | B24: =B36+B63 -> 9459 | C24: 0 | D24: =C24*B24 -> 0 | F24: NONE | H24: NONE | I24: =IF(AND(F24<>"NONE",H24<>"NONE", G24>0),VLOOKUP(H24,$A$52:$B$63,2,FALSE)-G24+VLOOKUP(H24,$A$25:$B$36,2,FALSE),"") | K24: ELITE PASAK | L24: ='DAILY STOCKS (SAT)'!R24 -> 2 | M24: =N10 -> 0 | N24: =P10 -> 3 | O24: =countif($F$3:$F$25,K24) -> 0 | Q24: =L24-M24+N24+O24+P24 -> 5 | R24: 3 | S24: =R24-Q24 -> -2 | Z24: 1 HOSE | AA24: 180
A25: REFILL | F25: NONE | H25: NONE | I25: =IF(AND(F25<>"NONE",H25<>"NONE", G25>0),VLOOKUP(H25,$A$52:$B$63,2,FALSE)-G25+VLOOKUP(H25,$A$25:$B$36,2,FALSE),"") | K25: ELITE RUSKAS | L25: ='DAILY STOCKS (SAT)'!R25 -> 64 | M25: =N11 -> 0 | N25: =P11 -> 0 | O25: =countif($F$3:$F$25,K25) -> 0 | Q25: =L25-M25+N25+O25+P25 -> 64 | R25: 62 | S25: =R25-Q25 -> -2 | Z25: 1 CLAMP | AA25: 20
A26: 2.7KG | B26: 280 | C26: 9 | D26: =C26*B26 -> 2520 | F26: TOTAL SALES | I26: =sum(I3:I25) -> 0 | K26: 22KG | L26: ='DAILY STOCKS (SAT)'!R26 -> 5 | M26: =N12 -> 0 | N26: =P12 -> 0 | O26: =countif($F$3:$F$25,K26) -> 0 | Q26: =L26-M26+N26+O26+P26 -> 5 | R26: 4 | S26: =R26-Q26 -> -1 | X26: 209571 | Y26: LYCU | Z26: 5 NGT | AA26: 4690 | AB26: 375
A27: 2.7KG FIESTA | B27: 280 | C27: 0 | D27: =C27*B27 -> 0 | K27: 50KG BLUE | L27: ='DAILY STOCKS (SAT)'!R27 -> 31 | M27: =N13 -> 3 | N27: =P13 -> 2 | O27: =countif($F$3:$F$25,K27) -> 0 | Q27: =L27-M27+N27+O27+P27 -> 30 | R27: 31 | S27: =R27-Q27 -> 1 | X27: 209572 | Y27: GABRAL | Z27: 1 2.7KG | AA27: 280
A28: 7KG PASAK | B28: 688 | C28: 0 | D28: =C28*B28 -> 0 | K28: 50KG CODED | L28: ='DAILY STOCKS (SAT)'!R28 -> 13 | M28: =N14 -> 7 | N28: =P14 -> 9 | O28: =countif($F$3:$F$25,K28) -> 0 | Q28: =L28-M28+N28+O28+P28 -> 15 | R28: 14 | S28: =R28-Q28 -> -1 | X28: 209573 | Y28: ROWENSON | Z28: 5 PV | AA28: 4540 | AB28: 525
A29: 7KG RUSKAS | B29: 688 | C29: 0 | D29: =C29*B29 -> 0 | Z29: 4 NGT | AA29: 3632 | AB29: 420
A30: 11KG PASAK | B30: 1013 | C30: 42 | D30: =C30*B30 -> 42546 | X30: 209574 | Y30: A&L | Z30: 5 NGT | AA30: 4615 | AB30: 450
A31: 11KG RUSKAS | B31: 1013 | C31: 48 | D31: =C31*B31 -> 48624 | K31: ACCESSORIES | L31: BEG | M31: DELIVERY | N31: SOLD | O31: DEFECTIVE | P31: END | Q31: AUD | R31: VAR | Z31: 5 PV | AA31: 4615 | AB31: 450
A32: ELITE PASAK | B32: 1038 | C32: 3 | D32: =C32*B32 -> 3114 | K32: REGULATOR | X32: 209575 | Y32: PACAMARA | Z32: 5 NGT | AA32: 4690 | AB32: 375
A33: ELITE RUSKAS | B33: 1038 | C33: 0 | D33: =C33*B33 -> 0 | K33: REGULATOR (PASAK) | L33: ='DAILY STOCKS (SAT)'!Q33 | M33: 0 | N33: =C4 -> 0 | P33: =L33+M33-N33-O33 -> 0 | R33: =Q33-P33 -> 0 | Z33: 3 PV | AA33: 2814 | AB33: 225
A34: 22KG | B34: 1965 | C34: 0 | D34: =C34*B34 -> 0 | K34: REGULATOR (RUSKAS) | L34: ='DAILY STOCKS (SAT)'!Q34 -> 11 | M34: 0 | N34: =C5 -> 4 | P34: =L34+M34-N34-O34 -> 7 | Q34: 7 | R34: =Q34-P34 -> 0 | X34: 209576 | Y34: EEB | Z34: 2 PV | AA34: 1876 | AB34: 150
A35: 50KG BLUE | B35: 4459 | C35: 2 | D35: =C35*B35 -> 8918 | K35: OTHERS | X35: 209578 | Y35: JOLLIBEE | Z35: 6 5OKG CODED | AC35: 26754
A36: 50KG CODED | B36: 4459 | C36: 9 | D36: =C36*B36 -> 40131 | K36: GS-3 | L36: ='DAILY STOCKS (SAT)'!Q36 -> 18 | M36: 0 | N36: =C7 -> 1 | P36: =L36+M36-N36-O36 -> 17 | Q36: 17 | R36: =Q36-P36 -> 0 | X36: 209579 | Y36: PETRON TIGAON | Z36: 5 PV | AB36: 375 | AC36: 4690
A37: BORROW | K37: HOSE | L37: ='DAILY STOCKS (SAT)'!Q37 -> 2 | M37: 0 | N37: =C8 -> 2 | P37: =L37+M37-N37-O37 -> 0 | R37: =Q37-P37 -> 0 | Z37: 5 NGT | AB37: 375 | AC37: 4690
A38: 2.7KG | B38: =B26 -> 280 | C38: 0 | D38: =C38*B38 -> 0 | K38: CLAMP | L38: ='DAILY STOCKS (SAT)'!Q38 -> 84 | M38: 0 | N38: =C9 -> 3 | P38: =L38+M38-N38-O38 -> 81 | Q38: 81 | R38: =Q38-P38 -> 0 | X38: 209580 | Y38: PETRON SANGAY | Z38: 5 PV | AB38: 375 | AC38: 4690
A39: 2.7KG FIESTA | B39: =B27 -> 280 | C39: 0 | D39: =C39*B39 -> 0 | K39: REYNA (SINGLE BURNER) | L39: ='DAILY STOCKS (SAT)'!Q39 | M39: 0 | N39: =C10 -> 0 | P39: =L39+M39-N39-O39 -> 0 | R39: =Q39-P39 -> 0 | Z39: 5 NGT | AB39: 375 | AC39: 4690
A40: 7KG PASAK | B40: =B28 -> 688 | C40: 0 | D40: =C40*B40 -> 0 | K40: REYNA (DOUBLE BURNER) | L40: ='DAILY STOCKS (SAT)'!Q40 | M40: 0 | N40: =C11 -> 0 | P40: =L40+M40-N40-O40 -> 0 | R40: =Q40-P40 -> 0 | X40: 209581 | Y40: ISRAEL | Z40: 1 PV | AA40: 988 | AB40: 25
A41: 7KG RUSKAS | B41: =B29 -> 688 | C41: 0 | D41: =C41*B41 -> 0 | K41: Y TYPE | L41: ='DAILY STOCKS (SAT)'!Q41 | M41: 0 | N41: =C12 -> 0 | P41: =L41+M41-N41-O41 -> 0 | R41: =Q41-P41 -> 0 | X41: 209583 | Y41: BETITO | Z41: 1 NGT | AA41: 988 | AB41: 25
A42: 11KG PASAK | B42: =B30 -> 1013 | C42: 0 | D42: =C42*B42 -> 0 | X42: 209584 | Y42: IGNACIO | Z42: 1 2.7KG | AA42: 280
A43: 11KG RUSKAS | B43: =B31 -> 1013 | C43: 0 | D43: =C43*B43 -> 0 | X43: 209585 | Y43: ALMARIO | Z43: 1 2.7KG | AA43: 280
A44: ELITE PASAK | B44: =B32 -> 1038 | C44: 0 | D44: =C44*B44 -> 0 | K44: TOTAL CYLINDER | L44: BEG | M44: END | N44: VAR | X44: 209586 | Y44: FLORIANO | Z44: 1 PV | AA44: 938 | AB44: 75
A45: ELITE RUSKAS | B45: =B33 -> 1038 | C45: 0 | D45: =C45*B45 -> 0 | K45: 2.7KG | L45: =L4+L18 -> 68 | M45: =T4+Q18 -> 67 | N45: =M45-L45 -> -1 | X45: 209587 | Y45: AMPONGAN | Z45: 1 PV | AA45: 938 | AB45: 75
A46: 22KG | B46: =B34 -> 1965 | C46: 0 | D46: =C46*B46 -> 0 | K46: 2.7KG FIESTA | L46: =L5+L19 -> 17 | M46: =T5+Q19 -> 17 | N46: =M46-L46 -> 0 | X46: 209588 | Y46: BRUCA | Z46: 1 2.7KG CYLINDER | AA46: 900
A47: 50KG BLUE | B47: =B35 -> 4459 | C47: 0 | D47: =C47*B47 -> 0 | K47: 7KG (PASAK) | L47: =L6+L20 -> 19 | M47: =T6+Q20 -> 19 | N47: =M47-L47 -> 0 | Z47: 1 2.7KG | AA47: 268 | AB47: 12
A48: 50KG CODED | B48: =B36 -> 4459 | C48: 0 | D48: =C48*B48 -> 0 | K48: 7KG (RUSKAS) | L48: =L7+L21 -> 31 | M48: =T7+Q21 -> 32 | N48: =M48-L48 -> 1 | Z48: 1 GS-3 | AA48: 650
A49: TOTAL SALES | D49: =sum(D4:D48) -> 155929 | K49: 11KG (PASAK) | L49: =L8+L22 -> 151 | M49: =T8+Q22 -> 151 | N49: =M49-L49 -> 0 | X49: 209589 | Y49: VALENZUELA | Z49: 1 PV | AA49: 938 | AB49: 75
K50: 11KG (RUSKAS) | L50: =L9+L23 -> 149 | M50: =T9+Q23 -> 147 | N50: =M50-L50 -> -2 | X50: 209590 | Y50: MANAOG | Z50: 1 NGT | AA50: 1013
K51: ELITE (PASAK) | L51: =L10+L24 -> 10 | M51: =T10+Q24 -> 10 | N51: =M51-L51 -> 0 | X51: 209591 | Y51: LUCASIA | Z51: 1 2.7KG | AA51: 268 | AB51: 12
A52: CYLINDER PRICE LIST | B52: PRICE | K52: ELITE (RUSKAS) | L52: =L11+L25 -> 75 | M52: =T11+Q25 -> 75 | N52: =M52-L52 -> 0 | X52: 209592 | Y52: LOBIA | Z52: 1 MREG | AA52: 375
A53: 2.7KG | B53: 1200 | K53: 22KG | L53: =L12+L26 -> 6 | M53: =T12+Q26 -> 6 | N53: =M53-L53 -> 0 | Z53: 1 HOSE | AA53: 180
A54: 2.7KG FIESTA | B54: 1200 | K54: 50KG (BLUE) | L54: =L13+L27 -> 31 | M54: =T13+Q27 -> 31 | N54: =M54-L54 -> 0 | Z54: 1 CLAMP | AA54: 20
A55: 7KG PASAK | B55: 1900 | K55: 50KG (CODED) | L55: =L14+L28 -> 16 | M55: =T14+Q28 -> 16 | N55: =M55-L55 -> 0 | X55: 209593 | Y55: TROYS | Z55: 1 50KG BLUE | AB55: 400 | AC55: 4059
A56: 7KG RUSKAS | B56: 1900 | X56: 209594 | Y56: EDNORMS | Z56: 1 PV | AA56: 938 | AB56: 75
A57: 11KG PASAK | B57: 2000 | X57: 209595 | Y57: MAPUTOL | Z57: 1 2.7KG | AA57: 280
A58: 11KG RUSKAS | B58: 2000 | K58: BORROWED | L58: BEG | M58: BORROWED | N58: RETURNED | O58: END | X58: 209500 | Y58: HW FRANCIA | Z58: 2 50KG CODED | AB58: 800 | AC58: 8118
A59: ELITE PASAK | B59: 3700 | K59: 2.7KG | L59: ='DAILY STOCKS (SAT)'!O59 -> 0 | M59: =R4 -> 0 | N59: =P18 | O59: =L59+M59-N59 -> 0 | X59: 207551 | Y59: GALVES | Z59: 1 NGT | AA59: 988 | AB59: 25
A60: ELITE RUSKAS | B60: 3700 | K60: 2.7KG FIESTA | L60: ='DAILY STOCKS (SAT)'!O60 -> 0 | M60: =R5 -> 0 | N60: =P19 | O60: =L60+M60-N60 -> 0 | X60: 207553 | Y60: CORTES | Z60: 1 PV | AA60: 1013
A61: 22KG | B61: 3700 | K61: 7KG (PASAK) | L61: ='DAILY STOCKS (SAT)'!O61 -> 0 | M61: =R6 -> 0 | N61: =P20 | O61: =L61+M61-N61 -> 0 | X61: 207554 | Y61: CABANAS | Z61: 1 NGT | AA61: 1013
A62: 50KG BLUE | B62: 5000 | K62: 7KG (RUSKAS) | L62: ='DAILY STOCKS (SAT)'!O62 -> 0 | M62: =R7 -> 0 | N62: =P21 -> 1 | O62: =L62+M62-N62 -> -1 | X62: 209555 | Y62: AMPONGAN | Z62: 1 PV | AA62: 938 | AB62: 75
A63: 50KG CODED | B63: 5000 | K63: 11KG (PASAK) | L63: ='DAILY STOCKS (SAT)'!O63 -> -1 | M63: =R8 -> 0 | N63: =P22 | O63: =L63+M63-N63 -> -1 | X63: 209556 | Y63: FERNANDO | Z63: 1 PV | AA63: 1013
K64: 11KG (RUSKAS) | L64: ='DAILY STOCKS (SAT)'!O64 -> 0 | M64: =R9 -> 0 | N64: =P23 | O64: =L64+M64-N64 -> 0 | X64: 209557 | Y64: JOAN | Z64: 1 NGT | AA64: 1013
K65: ELITE (PASAK) | L65: ='DAILY STOCKS (SAT)'!O65 -> 0 | M65: =R10 -> 0 | N65: =P24 | O65: =L65+M65-N65 -> 0 | X65: 209558 | Y65: PARONDA | Z65: 1 PV | AA65: 938 | AB65: 75
K66: ELITE (RUSKAS) | L66: ='DAILY STOCKS (SAT)'!O66 -> 0 | M66: =R11 -> 0 | N66: =P25 | O66: =L66+M66-N66 -> 0 | X66: 209559 | Y66: SEPTIMO | Z66: 1 PV | AA66: 1013
K67: 22KG | L67: ='DAILY STOCKS (SAT)'!O67 -> 0 | M67: =R12 -> 0 | N67: =P26 | O67: =L67+M67-N67 -> 0 | X67: 209560 | Y67: CORONEL | Z67: 1 NGT | AA67: 988 | AB67: 25
K68: 50KG (BLUE) | L68: ='DAILY STOCKS (SAT)'!O68 -> 0 | M68: =R13 -> 0 | N68: =P27 | O68: =L68+M68-N68 -> 0 | X68: 209561 | Y68: BNG | Z68: 1 50KG BLUE | AB68: 400 | AC68: 4059
K69: 50KG (CODED) | L69: ='DAILY STOCKS (SAT)'!O69 -> 0 | M69: =R14 -> 0 | N69: =P28 | O69: =L69+M69-N69 -> 0 | Z69: 3 NGT ELITE | AB69: 225 | AC69: 2889
X70: 209562 | Y70: ARAGDON | Z70: 1 PV CYLINDER | AA70: 600 | AE70: UPGRADE
Z71: 1 PV | AA71: 988 | AB71: 25
Z72: 1 MREG | AA72: 375
X73: 209563 | Y73: ABUNDABAR | Z73: 1 PV CYLINDER | AA73: 2000
Z74: 1 PV | AA74: 1000 | AB74: 13
Z75: 1 MREG | AA75: 375
Z76: 1 CLAMP | AA76: 20
X77: 209564 | Y77: ROSANES | Z77: 1 PV | AA77: 988 | AB77: 25
X78: 209565 | Y78: ARIJOLA | Z78: 1 2.7KG | AA78: 280
X79: 209566 | Y79: RAZADO | Z79: 1 2.7KG | AA79: 280
X80: 209567 | Y80: VICENTE | Z80: 1 PV | AA80: 988 | AB80: 25
X81: 209568 | Y81: CERDON | Z81: 1 NGT | AA81: 988 | AB81: 25
X105: TOTAL | AA105: =SUM(AA3:AA104) -> 83458 | AB105: =SUM(AB3:AB104) -> 8132 | AC105: =SUM(AC3:AC104) -> 64639 | AD105: =SUM(AD3:AD104) -> 0
